{"version": 0.6, "generator": "Overpass API 0.7.62.8 e802775f", "osm3s": {"timestamp_osm_base": "2025-11-17T18:29:14Z", "copyright": "The data included in this document is from www.openstreetmap.org. The data is made available under ODbL."}, "elements": [{"type": "node", "id": 7088114478, "lat": 46.3511984, "lon": 18.124748, "tags": {"man_made": "street_cabinet", "operator": "E.On", "power": "substation", "ref": "14084", "street_cabinet": "power", "substation": "minor_distribution", "utility": "power", "voltage": "22000;400"}}, {"type": "node", "id": 7088114479, "lat": 46.3510397, "lon": 18.1256944, "tags": {"man_made": "street_cabinet", "operator": "E.On", "power": "substation", "street_cabinet": "power", "substation": "minor_distribution", "utility": "power", "voltage": "22000;400"}}, {"type": "node", "id": 7141257077, "lat": 46.3692535, "lon": 18.1298647, "tags": {"man_made": "street_cabinet", "operator": "E.ON", "operator:wikidata": "Q270223", "power": "substation", "ref": "14064", "street_cabinet": "power", "substation": "minor_distribution", "utility": "power", "voltage": "22000;400"}}, {"type": "node", "id": 7254984465, "lat": 46.0533925, "lon": 18.2833686, "tags": {"man_made": "street_cabinet", "operator": "E.ON", "operator:wikidata": "Q270223", "power": "substation", "substation": "minor_distribution", "utility": "power"}}, {"type": "node", "id": 7254984467, "lat": 46.0533048, "lon": 18.2820549, "tags": {"man_made": "street_cabinet", "operator": "E.ON", "operator:wikidata": "Q270223", "power": "substation", "substation": "minor_distribution", "utility": "power"}}, {"type": "node", "id": 7276495487, "lat": 46.0646309, "lon": 18.1724782, "tags": {"man_made": "street_cabinet", "operator": "E.On", "power": "substation", "street_cabinet": "power", "substation": "minor_distribution", "utility": "power"}}, {"type": "node", "id": 9162279728, "lat": 46.3475121, "lon": 18.1142881, "tags": {"man_made": "street_cabinet", "power": "substation", "ref": "1", "street_cabinet": "power", "substation": "minor_distribution", "utility": "power", "voltage": "22000;400"}}, {"type": "node", "id": 9162279729, "lat": 46.3475228, "lon": 18.1143303, "tags": {"man_made": "street_cabinet", "power": "substation", "ref": "2", "street_cabinet": "power", "substation": "minor_distribution", "utility": "power", "voltage": "22000;400"}}, {"type": "node", "id": 12879214795, "lat": 46.3302046, "lon": 18.280041, "tags": {"man_made": "street_cabinet", "power": "substation", "ref": "1435", "substation": "minor_distribution", "utility": "power"}}, {"type": "node", "id": 12879214818, "lat": 46.3314491, "lon": 18.283766, "tags": {"man_made": "street_cabinet", "power": "substation", "ref": "14329", "substation": "minor_distribution", "utility": "power"}}, {"type": "node", "id": 12879649051, "lat": 46.3352056, "lon": 18.2911772, "tags": {"man_made": "street_cabinet", "power": "substation", "ref": "14328", "substation": "minor_distribution", "utility": "power"}}, {"type": "way", "id": 31538924, "bounds": {"minlat": 46.3703628, "minlon": 17.8160365, "maxlat": 46.3723671, "maxlon": 17.8184498}, "nodes": [3764655156, 3273669786, 352931604, 352931605, 352931607, 3764655156], "geometry": [{"lat": 46.3707569, "lon": 17.8184498}, {"lat": 46.3705198, "lon": 17.8175537}, {"lat": 46.3703628, "lon": 17.8169606}, {"lat": 46.3719362, "lon": 17.8160365}, {"lat": 46.3723671, "lon": 17.8175305}, {"lat": 46.3707569, "lon": 17.8184498}], "tags": {"barrier": "fence", "name": "Kaposv\u00e1r al\u00e1llom\u00e1s", "operator": "EDE", "power": "substation", "ref": "KAPV", "substation": "distribution", "voltage": "132000;22000"}}, {"type": "way", "id": 33846555, "bounds": {"minlat": 46.0770684, "minlon": 18.3048198, "maxlat": 46.0791743, "maxlon": 18.3080316}, "nodes": [387760968, 387760970, 387760971, 3222397549, 387760972, 387760968], "geometry": [{"lat": 46.0791743, "lon": 18.3071995}, {"lat": 46.0785092, "lon": 18.3048198}, {"lat": 46.0770684, "lon": 18.305655}, {"lat": 46.0772937, "lon": 18.3064569}, {"lat": 46.0777334, "lon": 18.3080316}, {"lat": 46.0791743, "lon": 18.3071995}], "tags": {"barrier": "fence", "frequency": "50", "location": "outdoor", "name": "P\u00e9cs  al\u00e1llom\u00e1s", "operator": "MAVIR", "operator:wikidata": "Q88272702", "operator:wikipedia": "sk:MAVIR", "power": "substation", "rating": "250 MVA", "ref": "P\u00c9CS", "substation": "transmission", "voltage": "400000;132000"}}, {"type": "way", "id": 38485068, "bounds": {"minlat": 45.7470785, "minlon": 18.1706019, "maxlat": 45.7490405, "maxlon": 18.172681}, "nodes": [455024355, 8300064107, 8300064104, 455024357, 455024358, 455024360, 455024362, 455024364, 8300119323, 8300064105, 455024355], "geometry": [{"lat": 45.7484455, "lon": 18.1710614}, {"lat": 45.7485396, "lon": 18.1710033}, {"lat": 45.7486271, "lon": 18.1709493}, {"lat": 45.7490405, "lon": 18.1721038}, {"lat": 45.7483384, "lon": 18.1725905}, {"lat": 45.7481975, "lon": 18.1721896}, {"lat": 45.7474683, "lon": 18.172681}, {"lat": 45.7470785, "lon": 18.1714062}, {"lat": 45.7475625, "lon": 18.1710838}, {"lat": 45.7482836, "lon": 18.1706019}, {"lat": 45.7484455, "lon": 18.1710614}], "tags": {"name": "TS Donji Miholjac", "operator": "Elektroslavonija", "power": "substation", "substation": "transmission", "voltage": "110000"}}, {"type": "way", "id": 113570302, "bounds": {"minlat": 46.4134123, "minlon": 17.8345094, "maxlat": 46.4157517, "maxlon": 17.8379887}, "nodes": [1287739839, 1287739856, 1287739877, 1287739881, 1287739903, 1287739852, 1287739885, 1287739837, 1287739989, 1287739847, 1287740006, 1287739839], "geometry": [{"lat": 46.4152114, "lon": 17.8379887}, {"lat": 46.4134123, "lon": 17.8370657}, {"lat": 46.4137101, "lon": 17.8358723}, {"lat": 46.4134808, "lon": 17.8357489}, {"lat": 46.4136231, "lon": 17.8352095}, {"lat": 46.4140096, "lon": 17.8349574}, {"lat": 46.4145053, "lon": 17.8352149}, {"lat": 46.4146902, "lon": 17.8345094}, {"lat": 46.4151172, "lon": 17.8347267}, {"lat": 46.4149675, "lon": 17.8353141}, {"lat": 46.4157517, "lon": 17.8357296}, {"lat": 46.4152114, "lon": 17.8379887}], "tags": {"barrier": "fence", "frequency": "50", "location": "outdoor", "name": "Topon\u00e1r al\u00e1llom\u00e1s", "operator": "MAVIR", "operator:wikidata": "Q88272702", "operator:wikipedia": "hu:MAVIR", "power": "substation", "rating": "250 MVA", "ref": "TOPN", "start_date": "1978", "substation": "transmission", "voltage": "400000;132000"}}, {"type": "way", "id": 113711302, "bounds": {"minlat": 45.7580428, "minlon": 18.6267155, "maxlat": 45.7595948, "maxlon": 18.6288953}, "nodes": [1289112017, 1289112022, 12918768571, 12918768595, 12918768590, 12918768600, 1289112024, 12918768596, 12918768593, 1289112026, 1289112017], "geometry": [{"lat": 45.7580428, "lon": 18.6279208}, {"lat": 45.7586869, "lon": 18.6288953}, {"lat": 45.7593062, "lon": 18.628048}, {"lat": 45.759341, "lon": 18.6280005}, {"lat": 45.7593871, "lon": 18.6279373}, {"lat": 45.7595336, "lon": 18.6277369}, {"lat": 45.7595948, "lon": 18.6276532}, {"lat": 45.7594515, "lon": 18.6274393}, {"lat": 45.7593385, "lon": 18.6272773}, {"lat": 45.7589665, "lon": 18.6267155}, {"lat": 45.7580428, "lon": 18.6279208}], "tags": {"barrier": "fence", "name": "TS Beli Manastir", "power": "substation", "substation": "transmission", "voltage": "110000"}}, {"type": "way", "id": 121241890, "bounds": {"minlat": 46.049255, "minlon": 17.8252731, "maxlat": 46.0503519, "maxlon": 17.8279544}, "nodes": [1357808255, 1357808193, 1357808194, 1357808222, 1357808256, 1357808197, 1357808195, 1357808192, 1357808164, 1357808255], "geometry": [{"lat": 46.0497125, "lon": 17.8252731}, {"lat": 46.0497828, "lon": 17.8268718}, {"lat": 46.0503054, "lon": 17.8268241}, {"lat": 46.0503519, "lon": 17.8278833}, {"lat": 46.0495712, "lon": 17.8279544}, {"lat": 46.0495345, "lon": 17.827117}, {"lat": 46.0495245, "lon": 17.8268895}, {"lat": 46.0493251, "lon": 17.8269077}, {"lat": 46.049255, "lon": 17.8253149}, {"lat": 46.0497125, "lon": 17.8252731}], "tags": {"barrier": "fence", "name": "Szigetv\u00e1r al\u00e1llom\u00e1s", "operator": "ETE", "power": "substation", "ref": "SZIG", "substation": "distribution", "voltage": "132000;22000"}}, {"type": "way", "id": 121501233, "bounds": {"minlat": 46.1822532, "minlon": 18.238129, "maxlat": 46.1824965, "maxlon": 18.2384597}, "nodes": [1359984889, 1359984901, 1359984896, 1359984880, 1359984889], "geometry": [{"lat": 46.1823257, "lon": 18.2384597}, {"lat": 46.1822532, "lon": 18.2383334}, {"lat": 46.182424, "lon": 18.238129}, {"lat": 46.1824965, "lon": 18.2382554}, {"lat": 46.1823257, "lon": 18.2384597}], "tags": {"building": "yes", "power": "substation", "source": "yahoo"}}, {"type": "way", "id": 121501391, "bounds": {"minlat": 46.1609264, "minlon": 18.2915615, "maxlat": 46.1622484, "maxlon": 18.2930425}, "nodes": [1359992295, 1359992278, 1359992302, 4363678138, 1359992320, 11197267233, 11197267232, 1359992279, 11197267231, 1359992314, 1359992284, 1359992295], "geometry": [{"lat": 46.1616962, "lon": 18.2915615}, {"lat": 46.1612159, "lon": 18.2917138}, {"lat": 46.1610947, "lon": 18.2916127}, {"lat": 46.1609264, "lon": 18.2920521}, {"lat": 46.1612531, "lon": 18.2922992}, {"lat": 46.1612074, "lon": 18.2924175}, {"lat": 46.1612987, "lon": 18.2925002}, {"lat": 46.1612402, "lon": 18.2926616}, {"lat": 46.1616264, "lon": 18.2929439}, {"lat": 46.1618406, "lon": 18.2930425}, {"lat": 46.1622484, "lon": 18.2919539}, {"lat": 46.1616962, "lon": 18.2915615}], "tags": {"alt_name": "Koszonya-tet\u0151", "barrier": "fence", "name": "Koml\u00f3 al\u00e1llom\u00e1s", "operator": "EDE", "power": "substation", "ref": "KOML", "substation": "distribution", "voltage": "132000;35000;22000"}}, {"type": "way", "id": 184500193, "bounds": {"minlat": 45.7828207, "minlon": 18.5929975, "maxlat": 45.7833225, "maxlon": 18.593511}, "nodes": [1949971366, 1949971356, 1949971362, 1949971350, 1949971366], "geometry": [{"lat": 45.7833225, "lon": 18.5930941}, {"lat": 45.7832797, "lon": 18.593511}, {"lat": 45.7828207, "lon": 18.5934357}, {"lat": 45.7828604, "lon": 18.5929975}, {"lat": 45.7833225, "lon": 18.5930941}], "tags": {"barrier": "fence", "fixme": "name", "power": "substation", "substation": "distribution"}}, {"type": "way", "id": 235409083, "bounds": {"minlat": 46.1816198, "minlon": 18.2377253, "maxlat": 46.1826928, "maxlon": 18.2390036}, "nodes": [1359984910, 1359984913, 1359984891, 1359984917, 1359984895, 1359984916, 1359984910], "geometry": [{"lat": 46.1826928, "lon": 18.2382526}, {"lat": 46.1820885, "lon": 18.2390036}, {"lat": 46.1816198, "lon": 18.2382791}, {"lat": 46.1819908, "lon": 18.2378066}, {"lat": 46.1823713, "lon": 18.2377253}, {"lat": 46.1826458, "lon": 18.2381755}, {"lat": 46.1826928, "lon": 18.2382526}], "tags": {"barrier": "fence", "name": "Sikonda al\u00e1llom\u00e1s", "operator": "EDE", "power": "substation", "ref": "SIKO", "substation": "distribution", "voltage": "132000;22000"}}, {"type": "way", "id": 254787562, "bounds": {"minlat": 46.0419354, "minlon": 18.2328534, "maxlat": 46.0432728, "maxlon": 18.2349195}, "nodes": [2605995661, 2605995662, 2605995663, 2605995664, 2845025622, 2605995661], "geometry": [{"lat": 46.0426334, "lon": 18.2328534}, {"lat": 46.0432728, "lon": 18.2342619}, {"lat": 46.0425748, "lon": 18.2349195}, {"lat": 46.0419354, "lon": 18.233511}, {"lat": 46.0422484, "lon": 18.2332187}, {"lat": 46.0426334, "lon": 18.2328534}], "tags": {"barrier": "fence", "name": "P\u00e9cs Kertv\u00e1ros al\u00e1llom\u00e1s", "operator": "EDE", "power": "substation", "ref": "KERT", "substation": "transmission", "voltage": "132000;22000"}}, {"type": "way", "id": 287812483, "bounds": {"minlat": 46.2982233, "minlon": 18.5042078, "maxlat": 46.2987339, "maxlon": 18.505934}, "nodes": [2913782329, 2913782330, 2913782331, 2913782332, 2913782329], "geometry": [{"lat": 46.2987192, "lon": 18.5042078}, {"lat": 46.2987339, "lon": 18.5059252}, {"lat": 46.2982379, "lon": 18.505934}, {"lat": 46.2982233, "lon": 18.5042167}, {"lat": 46.2987192, "lon": 18.5042078}], "tags": {"barrier": "fence", "name": "Bonyh\u00e1d al\u00e1llom\u00e1s", "operator": "EDE", "power": "substation", "ref": "BONY", "substation": "distribution", "voltage": "132000;22000"}}, {"type": "way", "id": 293373698, "bounds": {"minlat": 46.0603874, "minlon": 18.2022287, "maxlat": 46.0613273, "maxlon": 18.2036716}, "nodes": [2969610263, 2969610264, 2969610265, 2969610261, 3199311259, 2969610260, 2969610263], "geometry": [{"lat": 46.061103, "lon": 18.2022287}, {"lat": 46.0612781, "lon": 18.2029823}, {"lat": 46.0613273, "lon": 18.2034936}, {"lat": 46.0605276, "lon": 18.2036716}, {"lat": 46.0604794, "lon": 18.2032332}, {"lat": 46.0603874, "lon": 18.2023964}, {"lat": 46.061103, "lon": 18.2022287}], "tags": {"barrier": "fence", "name": "P\u00e9cs \u00dajmecsekalja al\u00e1llom\u00e1s", "power": "substation", "ref": "PUMA", "substation": "transmission"}}, {"type": "way", "id": 302192173, "bounds": {"minlat": 46.0633302, "minlon": 18.2641054, "maxlat": 46.0652604, "maxlon": 18.2653706}, "nodes": [3064409358, 3064409359, 11137139818, 3064409357, 11137139817, 3064409356, 3064409358], "geometry": [{"lat": 46.0652536, "lon": 18.2641054}, {"lat": 46.0652604, "lon": 18.2653317}, {"lat": 46.0634353, "lon": 18.2653706}, {"lat": 46.063383, "lon": 18.2653327}, {"lat": 46.0633432, "lon": 18.2652598}, {"lat": 46.0633302, "lon": 18.2641692}, {"lat": 46.0652536, "lon": 18.2641054}], "tags": {"barrier": "fence", "name": "P\u00e9cs Er\u0151m\u0171 al\u00e1llom\u00e1s", "operator": "Pannon H\u0151er\u0151m\u0171 Zrt.", "power": "substation", "ref": "P\u00c9CSE", "substation": "generation", "voltage": "132000"}}, {"type": "way", "id": 313889220, "bounds": {"minlat": 46.0546322, "minlon": 18.1085602, "maxlat": 46.0554578, "maxlon": 18.1097191}, "nodes": [3199311174, 3199311175, 3574857100, 3199311176, 3199311177, 3199311174], "geometry": [{"lat": 46.0546322, "lon": 18.1088264}, {"lat": 46.0548084, "lon": 18.1097191}, {"lat": 46.0552191, "lon": 18.1095429}, {"lat": 46.0554578, "lon": 18.109453}, {"lat": 46.0552815, "lon": 18.1085602}, {"lat": 46.0546322, "lon": 18.1088264}], "tags": {"barrier": "fence", "name": "K\u0151v\u00e1g\u00f3sz\u0151l\u0151s al\u00e1llom\u00e1s", "operator": "Mecsek \u00d6KO", "power": "substation", "ref": "KVSZ", "substation": "distribution", "voltage": "132000;35000"}}, {"type": "way", "id": 315669517, "bounds": {"minlat": 46.3803045, "minlon": 17.7759433, "maxlat": 46.3814323, "maxlon": 17.77741}, "nodes": [3218005846, 3218005847, 3218005848, 3218005849, 3218005846], "geometry": [{"lat": 46.3814323, "lon": 17.7772355}, {"lat": 46.3813274, "lon": 17.7759433}, {"lat": 46.3803045, "lon": 17.7761178}, {"lat": 46.3804094, "lon": 17.77741}, {"lat": 46.3814323, "lon": 17.7772355}], "tags": {"barrier": "fence", "name": "Kaposf\u00fcred al\u00e1llom\u00e1s", "operator": "M\u00c1V;EDE", "power": "substation", "ref": "KAFUM", "substation": "traction", "voltage": "132000;25000"}}, {"type": "way", "id": 315839275, "bounds": {"minlat": 45.8501196, "minlon": 18.3557582, "maxlat": 45.8509764, "maxlon": 18.3570993}, "nodes": [3219711745, 3219711749, 3219711750, 3219711746, 3219711747, 3219711748, 3219711745], "geometry": [{"lat": 45.8509248, "lon": 18.357033}, {"lat": 45.8507025, "lon": 18.3570143}, {"lat": 45.8506995, "lon": 18.3570993}, {"lat": 45.8501196, "lon": 18.3570406}, {"lat": 45.850182, "lon": 18.3557582}, {"lat": 45.8509764, "lon": 18.3558399}, {"lat": 45.8509248, "lon": 18.357033}], "tags": {"barrier": "fence", "name": "Sikl\u00f3s al\u00e1llom\u00e1s", "operator": "EDE", "power": "substation", "ref": "SIKL", "substation": "distribution", "voltage": "132000;22000"}}, {"type": "way", "id": 315953570, "bounds": {"minlat": 45.8113198, "minlon": 18.3997098, "maxlat": 45.8118889, "maxlon": 18.4004772}, "nodes": [3220750365, 3220750366, 3220750367, 3220750368, 3220750365], "geometry": [{"lat": 45.8118889, "lon": 18.4000767}, {"lat": 45.8115064, "lon": 18.4004772}, {"lat": 45.8113198, "lon": 18.4001103}, {"lat": 45.8117023, "lon": 18.3997098}, {"lat": 45.8118889, "lon": 18.4000767}], "tags": {"name": "Beremend al\u00e1llom\u00e1s", "operator": "DDC Kft.", "power": "substation", "ref": "BERE", "substation": "industrial", "voltage": "132000"}}, {"type": "way", "id": 316139877, "bounds": {"minlat": 46.0606611, "minlon": 18.2287308, "maxlat": 46.0608666, "maxlon": 18.2289507}, "nodes": [3222472193, 3222472194, 3222472195, 3222472196, 3222472193], "geometry": [{"lat": 46.0608666, "lon": 18.2288777}, {"lat": 46.0606903, "lon": 18.2289507}, {"lat": 46.0606611, "lon": 18.2288038}, {"lat": 46.0608373, "lon": 18.2287308}, {"lat": 46.0608666, "lon": 18.2288777}], "tags": {"description": "Valamikor 2018-2019-ben leszerelt\u00e9k a transzform\u00e1tort", "disused": "yes", "power": "substation", "substation": "industrial"}}, {"type": "way", "id": 330133883, "bounds": {"minlat": 46.0414878, "minlon": 18.2175, "maxlat": 46.0416218, "maxlon": 18.2178194}, "nodes": [3370939587, 3370939588, 3370939589, 3370939590, 3370939591, 3370939592, 3370941693, 6386357913, 3370941694, 3370939587], "geometry": [{"lat": 46.0415851, "lon": 18.2175}, {"lat": 46.0416218, "lon": 18.2176429}, {"lat": 46.0415859, "lon": 18.2176621}, {"lat": 46.0416135, "lon": 18.2177695}, {"lat": 46.0415201, "lon": 18.2178194}, {"lat": 46.0414878, "lon": 18.217694}, {"lat": 46.0415367, "lon": 18.2176679}, {"lat": 46.0415245, "lon": 18.2176205}, {"lat": 46.0415046, "lon": 18.217543}, {"lat": 46.0415851, "lon": 18.2175}], "tags": {"building": "service", "power": "substation", "substation": "minor_distribution", "utility": "power", "voltage": "22000;400"}}, {"type": "way", "id": 331140850, "bounds": {"minlat": 46.0863577, "minlon": 18.2553759, "maxlat": 46.0872869, "maxlon": 18.2565413}, "nodes": [3381995913, 3381995914, 3381995915, 3381995916, 3381995913], "geometry": [{"lat": 46.0865654, "lon": 18.2565413}, {"lat": 46.0863577, "lon": 18.2557912}, {"lat": 46.0870792, "lon": 18.2553759}, {"lat": 46.0872869, "lon": 18.2561259}, {"lat": 46.0865654, "lon": 18.2565413}], "tags": {"barrier": "fence", "name": "P\u00e9cs Kelet al\u00e1llom\u00e1s", "operator": "EDE", "power": "substation", "ref": "PECSK", "substation": "distribution", "voltage": "132000;11000"}}, {"type": "way", "id": 331463129, "bounds": {"minlat": 46.2215262, "minlon": 18.1052963, "maxlat": 46.2224072, "maxlon": 18.1062343}, "nodes": [3385391520, 3578355221, 3385391521, 3385391522, 3385391523, 3385391524, 3385391520], "geometry": [{"lat": 46.2224072, "lon": 18.105355}, {"lat": 46.2217891, "lon": 18.1053126}, {"lat": 46.221551, "lon": 18.1052963}, {"lat": 46.2215262, "lon": 18.1061952}, {"lat": 46.2223509, "lon": 18.1062343}, {"lat": 46.2223802, "lon": 18.1061626}, {"lat": 46.2224072, "lon": 18.105355}], "tags": {"name": "Mindszentgodisa al\u00e1llom\u00e1s", "operator": "M\u00c1V", "power": "substation", "ref": "MGODM", "substation": "traction", "voltage": "132000;25000"}}, {"type": "way", "id": 332973959, "bounds": {"minlat": 46.0691115, "minlon": 18.1128372, "maxlat": 46.0692807, "maxlon": 18.1131993}, "nodes": [3400933415, 3400933416, 3400933417, 3400933418, 3400933415], "geometry": [{"lat": 46.0692807, "lon": 18.1131564}, {"lat": 46.069172, "lon": 18.1131993}, {"lat": 46.0691115, "lon": 18.1128801}, {"lat": 46.0692202, "lon": 18.1128372}, {"lat": 46.0692807, "lon": 18.1131564}], "tags": {"building": "yes", "power": "substation", "substation": "minor_distribution", "voltage": "35000"}}, {"type": "way", "id": 335270085, "bounds": {"minlat": 46.0438266, "minlon": 18.213965, "maxlat": 46.0439302, "maxlon": 18.2141642}, "nodes": [3423851279, 3439247888, 3423849642, 3423849643, 3423849644, 3423851280, 3423851279], "geometry": [{"lat": 46.0438943, "lon": 18.2139903}, {"lat": 46.0438879, "lon": 18.213965}, {"lat": 46.0438266, "lon": 18.2139972}, {"lat": 46.0438689, "lon": 18.2141642}, {"lat": 46.0439302, "lon": 18.214132}, {"lat": 46.0439246, "lon": 18.2141098}, {"lat": 46.0438943, "lon": 18.2139903}], "tags": {"power": "substation"}}, {"type": "way", "id": 385950856, "bounds": {"minlat": 46.0393908, "minlon": 18.2188903, "maxlat": 46.0394784, "maxlon": 18.2190361}, "nodes": [3892924586, 3892924585, 3892924587, 3892924588, 3892924586], "geometry": [{"lat": 46.0394162, "lon": 18.2188903}, {"lat": 46.0393908, "lon": 18.2190083}, {"lat": 46.039453, "lon": 18.2190361}, {"lat": 46.0394784, "lon": 18.2189181}, {"lat": 46.0394162, "lon": 18.2188903}], "tags": {"building": "service", "power": "substation", "ref": "404", "substation": "minor_distribution", "utility": "power", "voltage": "22000;400"}}, {"type": "way", "id": 388709173, "bounds": {"minlat": 46.0394438, "minlon": 18.2255862, "maxlat": 46.0396711, "maxlon": 18.225916}, "nodes": [3918739998, 3918739995, 3918739999, 6383527663, 6383527664, 6383527665, 9885165054, 9885165053, 3918739998], "geometry": [{"lat": 46.039503, "lon": 18.2255862}, {"lat": 46.0394438, "lon": 18.2258586}, {"lat": 46.0395709, "lon": 18.225916}, {"lat": 46.0396033, "lon": 18.2257669}, {"lat": 46.0396549, "lon": 18.2257902}, {"lat": 46.0396711, "lon": 18.2257156}, {"lat": 46.0396136, "lon": 18.2256897}, {"lat": 46.0396242, "lon": 18.2256409}, {"lat": 46.039503, "lon": 18.2255862}], "tags": {"building": "service", "power": "substation", "substation": "minor_distribution", "utility": "power", "voltage": "22000;400"}}, {"type": "way", "id": 391162162, "bounds": {"minlat": 46.038457, "minlon": 18.2166892, "maxlat": 46.0385676, "maxlon": 18.216824}, "nodes": [3943327876, 3943327877, 3943327879, 3943327878, 3943327876], "geometry": [{"lat": 46.038457, "lon": 18.2167336}, {"lat": 46.0384788, "lon": 18.216824}, {"lat": 46.0385676, "lon": 18.2167796}, {"lat": 46.0385458, "lon": 18.2166892}, {"lat": 46.038457, "lon": 18.2167336}], "tags": {"building": "yes", "power": "substation", "source": "bing"}}, {"type": "way", "id": 440419958, "bounds": {"minlat": 46.0162837, "minlon": 17.9780003, "maxlat": 46.0173259, "maxlon": 17.9797356}, "nodes": [4381418626, 4381418627, 4381418628, 4381418648, 4381418629, 4381418636, 4381418626], "geometry": [{"lat": 46.0162837, "lon": 17.9793538}, {"lat": 46.0169542, "lon": 17.9797356}, {"lat": 46.0173259, "lon": 17.9783822}, {"lat": 46.0168986, "lon": 17.9781389}, {"lat": 46.0166553, "lon": 17.9780003}, {"lat": 46.0166349, "lon": 17.9780744}, {"lat": 46.0162837, "lon": 17.9793538}], "tags": {"barrier": "fence", "name": "Kir\u00e1lyegyh\u00e1za al\u00e1llom\u00e1s", "operator": "ETE", "power": "substation", "substation": "distribution", "voltage": "132000;22000"}}, {"type": "way", "id": 462227176, "bounds": {"minlat": 46.1889473, "minlon": 18.2632216, "maxlat": 46.1892035, "maxlon": 18.2635278}, "nodes": [4576324800, 4576324801, 4576324802, 4576324803, 4576324800], "geometry": [{"lat": 46.1892035, "lon": 18.2632937}, {"lat": 46.1889842, "lon": 18.2632216}, {"lat": 46.1889473, "lon": 18.2634557}, {"lat": 46.1891666, "lon": 18.2635278}, {"lat": 46.1892035, "lon": 18.2632937}], "tags": {"power": "substation", "substation": "generation", "voltage": "35000;6000"}}, {"type": "way", "id": 608462308, "bounds": {"minlat": 45.745849, "minlon": 18.0656548, "maxlat": 45.7458821, "maxlon": 18.0656937}, "nodes": [5764666464, 5764666465, 5764666466, 5764666467, 5764666464], "geometry": [{"lat": 45.7458805, "lon": 18.0656548}, {"lat": 45.745849, "lon": 18.0656576}, {"lat": 45.7458506, "lon": 18.0656937}, {"lat": 45.7458821, "lon": 18.0656909}, {"lat": 45.7458805, "lon": 18.0656548}], "tags": {"building": "service", "power": "substation", "substation": "minor_distribution"}}, {"type": "way", "id": 682117029, "bounds": {"minlat": 46.0429954, "minlon": 18.2135215, "maxlat": 46.0430852, "maxlon": 18.2136671}, "nodes": [6387802322, 6387802321, 6387802320, 6387802319, 6387802322], "geometry": [{"lat": 46.0430604, "lon": 18.2135215}, {"lat": 46.0430852, "lon": 18.2136385}, {"lat": 46.0430202, "lon": 18.2136671}, {"lat": 46.0429954, "lon": 18.2135501}, {"lat": 46.0430604, "lon": 18.2135215}], "tags": {"building": "service", "power": "substation", "substation": "minor_distribution", "utility": "power", "voltage": "22000;400"}}, {"type": "way", "id": 684134349, "bounds": {"minlat": 46.0373345, "minlon": 18.2294363, "maxlat": 46.0373658, "maxlon": 18.2294848}, "nodes": [6409022565, 6409022564, 6409022563, 6409022562, 6409022565], "geometry": [{"lat": 46.0373658, "lon": 18.2294516}, {"lat": 46.0373511, "lon": 18.2294848}, {"lat": 46.0373345, "lon": 18.2294695}, {"lat": 46.0373493, "lon": 18.2294363}, {"lat": 46.0373658, "lon": 18.2294516}], "tags": {"building": "service", "power": "substation", "substation": "minor_distribution", "utility": "power", "voltage": "22000;400"}}, {"type": "way", "id": 684134429, "bounds": {"minlat": 46.0376716, "minlon": 18.228665, "maxlat": 46.0377122, "maxlon": 18.228728}, "nodes": [6409023560, 6409023559, 6409023558, 6409023557, 6409023560], "geometry": [{"lat": 46.0377122, "lon": 18.2286849}, {"lat": 46.037693, "lon": 18.228728}, {"lat": 46.0376716, "lon": 18.2287081}, {"lat": 46.0376907, "lon": 18.228665}, {"lat": 46.0377122, "lon": 18.2286849}], "tags": {"description": "470. sz. Fellbach u. transzform\u00e1tor.", "power": "substation"}}, {"type": "way", "id": 684134441, "bounds": {"minlat": 46.0380453, "minlon": 18.2293105, "maxlat": 46.0380755, "maxlon": 18.229338}, "nodes": [6409023586, 6409023585, 6409023584, 6409023583, 6409023586], "geometry": [{"lat": 46.0380748, "lon": 18.2293105}, {"lat": 46.0380755, "lon": 18.2293364}, {"lat": 46.038046, "lon": 18.229338}, {"lat": 46.0380453, "lon": 18.2293122}, {"lat": 46.0380748, "lon": 18.2293105}], "tags": {"power": "substation"}}, {"type": "way", "id": 684374679, "bounds": {"minlat": 46.0522502, "minlon": 18.2169176, "maxlat": 46.0522878, "maxlon": 18.2169741}, "nodes": [6411747868, 6411747867, 6419106512, 6411747866, 6411747865, 6419106513, 6411747868], "geometry": [{"lat": 46.0522752, "lon": 18.2169176}, {"lat": 46.0522878, "lon": 18.2169578}, {"lat": 46.052283, "lon": 18.2169609}, {"lat": 46.0522628, "lon": 18.2169741}, {"lat": 46.0522502, "lon": 18.216934}, {"lat": 46.0522711, "lon": 18.2169203}, {"lat": 46.0522752, "lon": 18.2169176}], "tags": {"building": "service", "power": "substation", "substation": "minor_distribution", "utility": "power", "voltage": "22000;400"}}, {"type": "way", "id": 684639448, "bounds": {"minlat": 46.0456595, "minlon": 18.2162658, "maxlat": 46.0457423, "maxlon": 18.2163824}, "nodes": [6414856284, 6414856276, 6414856283, 6414856282, 6414856281, 6414856284], "geometry": [{"lat": 46.0457221, "lon": 18.2162658}, {"lat": 46.0457312, "lon": 18.2163043}, {"lat": 46.0457423, "lon": 18.2163518}, {"lat": 46.0456798, "lon": 18.2163824}, {"lat": 46.0456595, "lon": 18.2162964}, {"lat": 46.0457221, "lon": 18.2162658}], "tags": {"building": "service", "description": "Kamilla u. transzform\u00e1tor", "power": "substation", "substation": "minor_distribution", "utility": "power", "voltage": "22000;400"}}, {"type": "way", "id": 684805329, "bounds": {"minlat": 46.0572562, "minlon": 18.2341714, "maxlat": 46.0573025, "maxlon": 18.234234}, "nodes": [6416400261, 6416400260, 6416400259, 6416400258, 6416400261], "geometry": [{"lat": 46.0572881, "lon": 18.2341714}, {"lat": 46.0573025, "lon": 18.2341974}, {"lat": 46.0572706, "lon": 18.234234}, {"lat": 46.0572562, "lon": 18.234208}, {"lat": 46.0572881, "lon": 18.2341714}], "tags": {"power": "substation"}}, {"type": "way", "id": 684805330, "bounds": {"minlat": 46.0572961, "minlon": 18.2341265, "maxlat": 46.0573424, "maxlon": 18.2341891}, "nodes": [6416400265, 6416400264, 6416400263, 6416400262, 6416400265], "geometry": [{"lat": 46.057328, "lon": 18.2341265}, {"lat": 46.0573424, "lon": 18.2341525}, {"lat": 46.0573105, "lon": 18.2341891}, {"lat": 46.0572961, "lon": 18.2341631}, {"lat": 46.057328, "lon": 18.2341265}], "tags": {"power": "substation"}}, {"type": "way", "id": 692260620, "bounds": {"minlat": 46.066264, "minlon": 18.1931695, "maxlat": 46.066355, "maxlon": 18.1933067}, "nodes": [6498119037, 6498119036, 6498119035, 6498119034, 6498119037], "geometry": [{"lat": 46.0663224, "lon": 18.1931695}, {"lat": 46.066355, "lon": 18.1932656}, {"lat": 46.0662966, "lon": 18.1933067}, {"lat": 46.066264, "lon": 18.1932106}, {"lat": 46.0663224, "lon": 18.1931695}], "tags": {"building": "service", "power": "substation"}}, {"type": "way", "id": 724348844, "bounds": {"minlat": 46.3099008, "minlon": 18.1384575, "maxlat": 46.3099743, "maxlon": 18.1385866}, "nodes": [6793193298, 6793193299, 6793193300, 6793193301, 6793193298], "geometry": [{"lat": 46.3099743, "lon": 18.1384696}, {"lat": 46.3099634, "lon": 18.1385866}, {"lat": 46.3099008, "lon": 18.1385745}, {"lat": 46.3099117, "lon": 18.1384575}, {"lat": 46.3099743, "lon": 18.1384696}], "tags": {"power": "substation"}}, {"type": "way", "id": 744099737, "bounds": {"minlat": 46.1962974, "minlon": 18.2709352, "maxlat": 46.1963327, "maxlon": 18.2709795}, "nodes": [6964197119, 6964197118, 6964197117, 6964197116, 6964197119], "geometry": [{"lat": 46.1963327, "lon": 18.2709373}, {"lat": 46.1963314, "lon": 18.2709795}, {"lat": 46.1962974, "lon": 18.2709774}, {"lat": 46.1962987, "lon": 18.2709352}, {"lat": 46.1963327, "lon": 18.2709373}], "tags": {"power": "substation"}}, {"type": "way", "id": 766614057, "bounds": {"minlat": 45.8631591, "minlon": 17.9930572, "maxlat": 45.8632579, "maxlon": 17.9932316}, "nodes": [7159939754, 7159939755, 7159939756, 7159939757, 7159939754], "geometry": [{"lat": 45.8632579, "lon": 17.9930928}, {"lat": 45.8632015, "lon": 17.9930572}, {"lat": 45.8631591, "lon": 17.993196}, {"lat": 45.8632155, "lon": 17.9932316}, {"lat": 45.8632579, "lon": 17.9930928}], "tags": {"fixme": "Jobban kellene kategoriz\u00e1lni.", "operator": "E.On", "power": "substation"}}, {"type": "way", "id": 791848422, "bounds": {"minlat": 46.0392848, "minlon": 18.2162214, "maxlat": 46.0394248, "maxlon": 18.2163765}, "nodes": [7402677459, 7402677458, 7402677457, 7402677456, 7402677459], "geometry": [{"lat": 46.0394011, "lon": 18.2162214}, {"lat": 46.0394248, "lon": 18.2163161}, {"lat": 46.0393085, "lon": 18.2163765}, {"lat": 46.0392848, "lon": 18.2162818}, {"lat": 46.0394011, "lon": 18.2162214}], "tags": {"power": "substation"}}, {"type": "way", "id": 794392561, "bounds": {"minlat": 46.3523387, "minlon": 17.7811592, "maxlat": 46.3524588, "maxlon": 17.7812899}, "nodes": [7430097300, 7430097301, 7430097302, 7430097303, 7430097300], "geometry": [{"lat": 46.3524437, "lon": 17.7811592}, {"lat": 46.3523387, "lon": 17.7811941}, {"lat": 46.3523574, "lon": 17.7812899}, {"lat": 46.3524588, "lon": 17.7812548}, {"lat": 46.3524437, "lon": 17.7811592}], "tags": {"building": "service", "power": "substation", "substation": "minor_distribution"}}, {"type": "way", "id": 809337588, "bounds": {"minlat": 46.3682809, "minlon": 17.7944819, "maxlat": 46.3683654, "maxlon": 17.7945834}, "nodes": [7567518039, 7567518040, 7567518041, 7567518042, 7567518039], "geometry": [{"lat": 46.3683632, "lon": 17.7944819}, {"lat": 46.3683654, "lon": 17.7945754}, {"lat": 46.3682842, "lon": 17.7945834}, {"lat": 46.3682809, "lon": 17.79449}, {"lat": 46.3683632, "lon": 17.7944819}], "tags": {"power": "substation", "substation": "minor_distribution"}}, {"type": "way", "id": 809586074, "bounds": {"minlat": 46.0481458, "minlon": 18.2137499, "maxlat": 46.048225, "maxlon": 18.2138337}, "nodes": [7569741274, 7569741273, 7569741272, 7569741271, 7569741274], "geometry": [{"lat": 46.0482144, "lon": 18.2137499}, {"lat": 46.048225, "lon": 18.2138076}, {"lat": 46.0481564, "lon": 18.2138337}, {"lat": 46.0481458, "lon": 18.2137759}, {"lat": 46.0482144, "lon": 18.2137499}], "tags": {"building": "service", "power": "substation", "substation": "minor_distribution", "utility": "power", "voltage": "22000;400"}}, {"type": "way", "id": 891250119, "bounds": {"minlat": 46.3748022, "minlon": 17.8423842, "maxlat": 46.3758432, "maxlon": 17.843894}, "nodes": [8283710745, 8283710746, 8283710747, 8283710748, 8283710745], "geometry": [{"lat": 46.3753333, "lon": 17.8423842}, {"lat": 46.3748022, "lon": 17.8431075}, {"lat": 46.375312, "lon": 17.843894}, {"lat": 46.3758432, "lon": 17.8431706}, {"lat": 46.3753333, "lon": 17.8423842}], "tags": {"name": "Kaposv\u00e1r Kelet al\u00e1llom\u00e1s", "power": "substation", "ref": "KPVK", "substation": "generation", "voltage": "132000"}}, {"type": "way", "id": 899929916, "bounds": {"minlat": 46.0398298, "minlon": 17.9965969, "maxlat": 46.0398552, "maxlon": 17.9966448}, "nodes": [8361260900, 8361260899, 8361260898, 8361260897, 8361260900], "geometry": [{"lat": 46.0398533, "lon": 17.9965969}, {"lat": 46.0398552, "lon": 17.9966428}, {"lat": 46.0398317, "lon": 17.9966448}, {"lat": 46.0398298, "lon": 17.9965989}, {"lat": 46.0398533, "lon": 17.9965969}], "tags": {"building": "yes", "location": "outdoor", "operator": "E.On", "power": "substation"}}, {"type": "way", "id": 902421087, "bounds": {"minlat": 46.0492326, "minlon": 18.2289617, "maxlat": 46.0492718, "maxlon": 18.2289938}, "nodes": [8381822306, 8381822303, 8381822304, 8381822305, 8381822306], "geometry": [{"lat": 46.0492713, "lon": 18.2289617}, {"lat": 46.0492718, "lon": 18.2289925}, {"lat": 46.0492332, "lon": 18.2289938}, {"lat": 46.0492326, "lon": 18.228963}, {"lat": 46.0492713, "lon": 18.2289617}], "tags": {"building": "yes", "location": "outdoor", "operator": "E.On", "power": "substation"}}, {"type": "way", "id": 919850587, "bounds": {"minlat": 46.3723041, "minlon": 17.7793156, "maxlat": 46.3723512, "maxlon": 17.7794001}, "nodes": [8542004084, 8542004085, 8542004086, 8542004087, 8542004084], "geometry": [{"lat": 46.3723464, "lon": 17.7793156}, {"lat": 46.3723512, "lon": 17.7793947}, {"lat": 46.3723088, "lon": 17.7794001}, {"lat": 46.3723041, "lon": 17.779321}, {"lat": 46.3723464, "lon": 17.7793156}], "tags": {"building": "yes", "power": "substation"}}, {"type": "way", "id": 921543052, "bounds": {"minlat": 46.3696448, "minlon": 17.779271, "maxlat": 46.3696921, "maxlon": 17.7793864}, "nodes": [8555655186, 8555655187, 8555655188, 8555655189, 8555655186], "geometry": [{"lat": 46.3696846, "lon": 17.779271}, {"lat": 46.3696921, "lon": 17.7793806}, {"lat": 46.3696523, "lon": 17.7793864}, {"lat": 46.3696448, "lon": 17.7792768}, {"lat": 46.3696846, "lon": 17.779271}], "tags": {"building": "yes", "power": "substation"}}, {"type": "way", "id": 996123771, "bounds": {"minlat": 46.1557522, "minlon": 18.4156209, "maxlat": 46.155865, "maxlon": 18.415775}, "nodes": [9198104178, 9198104179, 9198104180, 9198104181, 9198104187, 9198104184, 9198104183, 9198104178], "geometry": [{"lat": 46.1558297, "lon": 18.415775}, {"lat": 46.155865, "lon": 18.4157137}, {"lat": 46.1557874, "lon": 18.4156209}, {"lat": 46.1557522, "lon": 18.4156822}, {"lat": 46.1557714, "lon": 18.4157052}, {"lat": 46.1557893, "lon": 18.4157266}, {"lat": 46.1558174, "lon": 18.4157602}, {"lat": 46.1558297, "lon": 18.415775}], "tags": {"building": "transformer_tower", "power": "substation", "substation": "minor_distribution", "voltage": "22000;400"}}, {"type": "way", "id": 1013211909, "bounds": {"minlat": 46.3626082, "minlon": 17.7838882, "maxlat": 46.3626868, "maxlon": 17.78398}, "nodes": [9347719676, 9347719677, 9347719678, 9347719679, 9347719676], "geometry": [{"lat": 46.3626759, "lon": 17.7838882}, {"lat": 46.3626082, "lon": 17.7839104}, {"lat": 46.3626191, "lon": 17.78398}, {"lat": 46.3626868, "lon": 17.7839579}, {"lat": 46.3626759, "lon": 17.7838882}], "tags": {"building": "yes", "power": "substation"}}, {"type": "way", "id": 1071340216, "bounds": {"minlat": 45.9930468, "minlon": 18.2327918, "maxlat": 45.9930945, "maxlon": 18.2328283}, "nodes": [9831592436, 9831592437, 9831592438, 9831592439, 9831592436], "geometry": [{"lat": 45.9930945, "lon": 18.2327994}, {"lat": 45.9930921, "lon": 18.2328283}, {"lat": 45.9930468, "lon": 18.2328206}, {"lat": 45.9930491, "lon": 18.2327918}, {"lat": 45.9930945, "lon": 18.2327994}], "tags": {"power": "substation", "substation": "minor_distribution"}}, {"type": "way", "id": 1078209666, "bounds": {"minlat": 46.0382797, "minlon": 18.2268145, "maxlat": 46.0383679, "maxlon": 18.2269585}, "nodes": [3892924582, 9885165086, 9885165085, 3892924581, 3892924582], "geometry": [{"lat": 46.0383679, "lon": 18.2268423}, {"lat": 46.0383044, "lon": 18.2268145}, {"lat": 46.0382797, "lon": 18.2269307}, {"lat": 46.0383432, "lon": 18.2269585}, {"lat": 46.0383679, "lon": 18.2268423}], "tags": {"building": "service", "power": "substation", "substation": "minor_distribution", "utility": "power", "voltage": "22000;400"}}, {"type": "way", "id": 1078783254, "bounds": {"minlat": 46.0266294, "minlon": 18.2233814, "maxlat": 46.0266974, "maxlon": 18.2234429}, "nodes": [9889505588, 9889505587, 9889505586, 9889505585, 9889505588], "geometry": [{"lat": 46.0266964, "lon": 18.2233814}, {"lat": 46.0266974, "lon": 18.2234405}, {"lat": 46.0266304, "lon": 18.2234429}, {"lat": 46.0266294, "lon": 18.2233839}, {"lat": 46.0266964, "lon": 18.2233814}], "tags": {"building": "service", "power": "substation", "ref": "11992", "substation": "minor_distribution", "utility": "power", "voltage": "22000;400"}}, {"type": "way", "id": 1078783255, "bounds": {"minlat": 46.0293464, "minlon": 18.2231468, "maxlat": 46.0294144, "maxlon": 18.2232082}, "nodes": [9889505592, 9889505591, 9889505590, 9889505589, 9889505592], "geometry": [{"lat": 46.0294134, "lon": 18.2231468}, {"lat": 46.0294144, "lon": 18.2232058}, {"lat": 46.0293474, "lon": 18.2232082}, {"lat": 46.0293464, "lon": 18.2231492}, {"lat": 46.0294134, "lon": 18.2231468}], "tags": {"building": "service", "power": "substation", "ref": "11969", "substation": "minor_distribution", "utility": "power", "voltage": "22000;400"}}, {"type": "way", "id": 1078783256, "bounds": {"minlat": 46.0274963, "minlon": 18.2230886, "maxlat": 46.0275643, "maxlon": 18.2231501}, "nodes": [9889505596, 9889505595, 9889505594, 9889505593, 9889505596], "geometry": [{"lat": 46.0275633, "lon": 18.2230886}, {"lat": 46.0275643, "lon": 18.2231476}, {"lat": 46.0274973, "lon": 18.2231501}, {"lat": 46.0274963, "lon": 18.223091}, {"lat": 46.0275633, "lon": 18.2230886}], "tags": {"building": "service", "power": "substation", "ref": "11993", "substation": "minor_distribution", "utility": "power", "voltage": "22000;400"}}, {"type": "way", "id": 1078786251, "bounds": {"minlat": 46.0434415, "minlon": 18.2295309, "maxlat": 46.0435112, "maxlon": 18.2296271}, "nodes": [9889552926, 9876603080, 9889552925, 9889552924, 9889552926], "geometry": [{"lat": 46.0435071, "lon": 18.2295309}, {"lat": 46.0435112, "lon": 18.2296209}, {"lat": 46.0434456, "lon": 18.2296271}, {"lat": 46.0434415, "lon": 18.2295371}, {"lat": 46.0435071, "lon": 18.2295309}], "tags": {"building": "service", "power": "substation", "ref": "429", "substation": "minor_distribution", "utility": "power", "voltage": "22000;400"}}, {"type": "way", "id": 1078786254, "bounds": {"minlat": 46.0419999, "minlon": 18.2301212, "maxlat": 46.0420952, "maxlon": 18.2302399}, "nodes": [6385893528, 6385893527, 6385893534, 6385893533, 6385893532, 6385893528], "geometry": [{"lat": 46.0420003, "lon": 18.2301779}, {"lat": 46.0420009, "lon": 18.2302399}, {"lat": 46.0420952, "lon": 18.2302383}, {"lat": 46.0420942, "lon": 18.2301212}, {"lat": 46.0419999, "lon": 18.2301228}, {"lat": 46.0420003, "lon": 18.2301779}], "tags": {"building": "service", "power": "substation", "substation": "minor_distribution", "utility": "power", "voltage": "22000;400"}}, {"type": "way", "id": 1079226368, "bounds": {"minlat": 45.8508124, "minlon": 18.2971923, "maxlat": 45.850891, "maxlon": 18.2972754}, "nodes": [9578975443, 9893264760, 9893264759, 9893264758, 9578975443], "geometry": [{"lat": 45.850891, "lon": 18.2972107}, {"lat": 45.8508206, "lon": 18.2971923}, {"lat": 45.8508124, "lon": 18.2972571}, {"lat": 45.8508828, "lon": 18.2972754}, {"lat": 45.850891, "lon": 18.2972107}], "tags": {"building": "service", "power": "substation", "substation": "minor_distribution"}}, {"type": "way", "id": 1079226377, "bounds": {"minlat": 45.850824, "minlon": 18.2984052, "maxlat": 45.85084, "maxlon": 18.2984392}, "nodes": [9893264788, 9893264787, 9893264786, 9893264785, 9893264788], "geometry": [{"lat": 45.8508289, "lon": 18.2984052}, {"lat": 45.850824, "lon": 18.2984355}, {"lat": 45.8508351, "lon": 18.2984392}, {"lat": 45.85084, "lon": 18.2984089}, {"lat": 45.8508289, "lon": 18.2984052}], "tags": {"power": "substation", "substation": "minor_distribution"}}, {"type": "way", "id": 1079226378, "bounds": {"minlat": 45.8504921, "minlon": 18.2982488, "maxlat": 45.8505148, "maxlon": 18.2982681}, "nodes": [9893264792, 9893264791, 9893264790, 9893264789, 9893264792], "geometry": [{"lat": 45.8505148, "lon": 18.2982519}, {"lat": 45.8504932, "lon": 18.2982488}, {"lat": 45.8504921, "lon": 18.298265}, {"lat": 45.8505137, "lon": 18.2982681}, {"lat": 45.8505148, "lon": 18.2982519}], "tags": {"power": "substation", "substation": "minor_distribution"}}, {"type": "way", "id": 1079703711, "bounds": {"minlat": 46.0270191, "minlon": 18.2219946, "maxlat": 46.0271178, "maxlon": 18.2221287}, "nodes": [9896974362, 9896974361, 9896974360, 9896974359, 9896974362], "geometry": [{"lat": 46.0271178, "lon": 18.2219946}, {"lat": 46.0271178, "lon": 18.2221287}, {"lat": 46.0270191, "lon": 18.2221287}, {"lat": 46.0270191, "lon": 18.2219946}, {"lat": 46.0271178, "lon": 18.2219946}], "tags": {"building": "service", "power": "substation", "substation": "minor_distribution", "utility": "power", "voltage": "22000;400"}}, {"type": "way", "id": 1079704923, "bounds": {"minlat": 46.0280854, "minlon": 18.2209875, "maxlat": 46.0281392, "maxlon": 18.2211019}, "nodes": [9896959043, 9896959040, 9896959041, 9896959042, 9896959043], "geometry": [{"lat": 46.0281392, "lon": 18.2211001}, {"lat": 46.0280872, "lon": 18.2211019}, {"lat": 46.0280854, "lon": 18.2209893}, {"lat": 46.0281374, "lon": 18.2209875}, {"lat": 46.0281392, "lon": 18.2211001}], "tags": {"building": "service", "power": "substation", "ref": "12009", "substation": "minor_distribution", "utility": "power", "voltage": "22000;400"}}, {"type": "way", "id": 1084304576, "bounds": {"minlat": 46.3670421, "minlon": 17.781601, "maxlat": 46.3671291, "maxlon": 17.7816801}, "nodes": [9936174517, 9936174518, 9936174519, 9936174520, 9936174517], "geometry": [{"lat": 46.3671246, "lon": 17.781601}, {"lat": 46.3671291, "lon": 17.7816684}, {"lat": 46.3670466, "lon": 17.7816801}, {"lat": 46.3670421, "lon": 17.7816126}, {"lat": 46.3671246, "lon": 17.781601}], "tags": {"building": "yes", "power": "substation"}}, {"type": "way", "id": 1089886957, "bounds": {"minlat": 46.1639894, "minlon": 18.4102491, "maxlat": 46.164023, "maxlon": 18.4103072}, "nodes": [9983585977, 9983585976, 9983585975, 9983585974, 9983585977], "geometry": [{"lat": 46.164023, "lon": 18.4102969}, {"lat": 46.1639994, "lon": 18.4103072}, {"lat": 46.1639894, "lon": 18.4102595}, {"lat": 46.164013, "lon": 18.4102491}, {"lat": 46.164023, "lon": 18.4102969}], "tags": {"power": "substation", "substation": "minor_distribution"}}, {"type": "way", "id": 1144181862, "bounds": {"minlat": 45.7348438, "minlon": 17.7458335, "maxlat": 45.7349013, "maxlon": 17.7459191}, "nodes": [10650434820, 10650434821, 10650434822, 10650434823, 10650434820], "geometry": [{"lat": 45.7348726, "lon": 17.7458335}, {"lat": 45.7348438, "lon": 17.7458646}, {"lat": 45.7348725, "lon": 17.7459191}, {"lat": 45.7349013, "lon": 17.7458879}, {"lat": 45.7348726, "lon": 17.7458335}], "tags": {"building": "service", "power": "substation"}}, {"type": "way", "id": 1204472467, "bounds": {"minlat": 45.855797, "minlon": 18.4337403, "maxlat": 45.8558542, "maxlon": 18.4338218}, "nodes": [11163347458, 11163347459, 11163347460, 11163347461, 11163347458], "geometry": [{"lat": 45.8558542, "lon": 18.4337857}, {"lat": 45.8558209, "lon": 18.4337403}, {"lat": 45.855797, "lon": 18.4337764}, {"lat": 45.8558302, "lon": 18.4338218}, {"lat": 45.8558542, "lon": 18.4337857}], "tags": {"power": "substation"}}, {"type": "way", "id": 1337755852, "bounds": {"minlat": 46.0724808, "minlon": 18.2679798, "maxlat": 46.0725216, "maxlon": 18.2680347}, "nodes": [12374070956, 12374070955, 12374070954, 12374070953, 12374070956], "geometry": [{"lat": 46.0725216, "lon": 18.2680084}, {"lat": 46.0724939, "lon": 18.2680347}, {"lat": 46.0724808, "lon": 18.2680061}, {"lat": 46.0725085, "lon": 18.2679798}, {"lat": 46.0725216, "lon": 18.2680084}], "tags": {"man_made": "street_cabinet", "power": "substation", "substation": "minor_distribution"}}, {"type": "way", "id": 1384445634, "bounds": {"minlat": 46.0566362, "minlon": 18.2105603, "maxlat": 46.0567105, "maxlon": 18.2106664}, "nodes": [12817988381, 12817988380, 12817988379, 12817988378, 12817988381], "geometry": [{"lat": 46.0567105, "lon": 18.2106231}, {"lat": 46.0566818, "lon": 18.2106664}, {"lat": 46.0566362, "lon": 18.2106036}, {"lat": 46.056665, "lon": 18.2105603}, {"lat": 46.0567105, "lon": 18.2106231}], "tags": {"power": "substation", "substation": "minor_distribution"}}, {"type": "way", "id": 1387460182, "bounds": {"minlat": 46.3758833, "minlon": 18.1338775, "maxlat": 46.3759104, "maxlon": 18.1339311}, "nodes": [12843703901, 12843695985, 12843695976, 12843695993, 12843703901], "geometry": [{"lat": 46.3759094, "lon": 18.1338775}, {"lat": 46.3758833, "lon": 18.1338785}, {"lat": 46.3758843, "lon": 18.1339311}, {"lat": 46.3759104, "lon": 18.1339301}, {"lat": 46.3759094, "lon": 18.1338775}], "tags": {"building": "service", "power": "substation", "ref": "14066", "substation": "minor_distribution"}}, {"type": "relation", "id": 3326245, "bounds": {"minlat": 46.3787237, "minlon": 18.114021, "maxlat": 46.3799734, "maxlon": 18.1164328}, "members": [{"type": "way", "ref": 710526845, "role": "outer", "geometry": [{"lat": 46.3790945, "lon": 18.1155297}, {"lat": 46.3793887, "lon": 18.1164328}]}, {"type": "way", "ref": 1180752295, "role": "outer", "geometry": [{"lat": 46.3793887, "lon": 18.1164328}, {"lat": 46.3799734, "lon": 18.1160127}, {"lat": 46.3797925, "lon": 18.1154326}]}, {"type": "way", "ref": 727039282, "role": "outer", "geometry": [{"lat": 46.3797925, "lon": 18.1154326}, {"lat": 46.379309, "lon": 18.114021}, {"lat": 46.3787237, "lon": 18.1144738}, {"lat": 46.3790945, "lon": 18.1155297}]}], "tags": {"barrier": "fence", "name": "Domb\u00f3v\u00e1r al\u00e1llom\u00e1s", "operator": "EDE", "power": "substation", "ref": "DOMB", "substation": "distribution", "type": "multipolygon", "voltage": "132000;22000"}}]}