{"version": 0.6, "generator": "Overpass API 0.7.62.8 e802775f", "osm3s": {"timestamp_osm_base": "2025-10-30T01:31:19Z", "copyright": "The data included in this document is from www.openstreetmap.org. The data is made available under ODbL."}, "elements": [{"type": "node", "id": 652868438, "lat": 37.955393, "lon": -8.8628153, "tags": {"leisure": "sports_centre", "name": "IOS"}}, {"type": "node", "id": 655309038, "lat": 37.9605468, "lon": -8.8769405}, {"type": "node", "id": 655309039, "lat": 37.9602919, "lon": -8.8765248}, {"type": "node", "id": 655309041, "lat": 37.9601058, "lon": -8.8767084}, {"type": "node", "id": 655309043, "lat": 37.9603607, "lon": -8.8771241}, {"type": "node", "id": 655309047, "lat": 37.9592077, "lon": -8.8715615}, {"type": "node", "id": 655309048, "lat": 37.9582306, "lon": -8.8710378}, {"type": "node", "id": 655309049, "lat": 37.9585177, "lon": -8.8701865}, {"type": "node", "id": 655309051, "lat": 37.9594927, "lon": -8.8707181}, {"type": "node", "id": 881633443, "lat": 37.9570629, "lon": -8.8637388}, {"type": "node", "id": 1190104140, "lat": 37.9605739, "lon": -8.8723094}, {"type": "node", "id": 1190104148, "lat": 37.9608137, "lon": -8.8724218}, {"type": "node", "id": 1190104161, "lat": 37.9580421, "lon": -8.8696344}, {"type": "node", "id": 1190104184, "lat": 37.9579842, "lon": -8.869783}, {"type": "node", "id": 1190104185, "lat": 37.9580531, "lon": -8.8717875}, {"type": "node", "id": 1190104196, "lat": 37.9609548, "lon": -8.8719346}, {"type": "node", "id": 1190104209, "lat": 37.9578854, "lon": -8.8697137}, {"type": "node", "id": 1190104210, "lat": 37.9580893, "lon": -8.8716596}, {"type": "node", "id": 1190104218, "lat": 37.9577765, "lon": -8.8699798}, {"type": "node", "id": 1190104223, "lat": 37.9607191, "lon": -8.8718221}, {"type": "node", "id": 1190104264, "lat": 37.9579378, "lon": -8.8695722}, {"type": "node", "id": 1190104266, "lat": 37.9579457, "lon": -8.8715942}, {"type": "node", "id": 1744157072, "lat": 37.9557056, "lon": -8.8641654}, {"type": "node", "id": 1745543493, "lat": 37.9577082, "lon": -8.8678576}, {"type": "node", "id": 1745543666, "lat": 37.9578207, "lon": -8.8692143}, {"type": "node", "id": 1745730880, "lat": 37.9592882, "lon": -8.864753}, {"type": "node", "id": 1746573759, "lat": 37.9576025, "lon": -8.8787244}, {"type": "node", "id": 1746573785, "lat": 37.9568158, "lon": -8.8809767}, {"type": "node", "id": 1746641098, "lat": 37.9588838, "lon": -8.8648506}, {"type": "node", "id": 1746641180, "lat": 37.9587681, "lon": -8.8653276}, {"type": "node", "id": 1746641199, "lat": 37.9588082, "lon": -8.8656038}, {"type": "node", "id": 1746641213, "lat": 37.958895, "lon": -8.8648044}, {"type": "node", "id": 1746641216, "lat": 37.958877, "lon": -8.8648787}, {"type": "node", "id": 1746641248, "lat": 37.959543, "lon": -8.8637178}, {"type": "node", "id": 1746641275, "lat": 37.9594367, "lon": -8.8635847}, {"type": "node", "id": 1746641285, "lat": 37.9594836, "lon": -8.8636567}, {"type": "node", "id": 1746641300, "lat": 37.9588439, "lon": -8.8666082}, {"type": "node", "id": 1746641318, "lat": 37.9588665, "lon": -8.8653664}, {"type": "node", "id": 1746641320, "lat": 37.9584097, "lon": -8.8659794}, {"type": "node", "id": 1746641324, "lat": 37.9591308, "lon": -8.8653987}, {"type": "node", "id": 1746641338, "lat": 37.9583191, "lon": -8.8659405}, {"type": "node", "id": 1746641362, "lat": 37.959051, "lon": -8.8641054}, {"type": "node", "id": 1746641406, "lat": 37.9586861, "lon": -8.8648369}, {"type": "node", "id": 1746641407, "lat": 37.9587099, "lon": -8.865565}, {"type": "node", "id": 1746641413, "lat": 37.9590447, "lon": -8.8641861}, {"type": "node", "id": 1986259630, "lat": 37.9552893, "lon": -8.8668584}, {"type": "node", "id": 2491171229, "lat": 37.9576179, "lon": -8.866682}, {"type": "node", "id": 2491171231, "lat": 37.9576183, "lon": -8.867462}, {"type": "node", "id": 2491171234, "lat": 37.9576426, "lon": -8.8674809}, {"type": "node", "id": 2491171236, "lat": 37.9576628, "lon": -8.8674819}, {"type": "node", "id": 2491171239, "lat": 37.9576839, "lon": -8.86747}, {"type": "node", "id": 2491171242, "lat": 37.957906, "lon": -8.8666657}, {"type": "node", "id": 2586594704, "lat": 37.9577672, "lon": -8.8677914}, {"type": "node", "id": 2627816820, "lat": 37.9655085, "lon": -8.8580041}, {"type": "node", "id": 2627816823, "lat": 37.9652239, "lon": -8.8575618}, {"type": "node", "id": 2627816834, "lat": 37.9654966, "lon": -8.8580477}, {"type": "node", "id": 2627816836, "lat": 37.9649954, "lon": -8.8578212}, {"type": "node", "id": 2648832737, "lat": 37.9654664, "lon": -8.8579386}, {"type": "node", "id": 2689090907, "lat": 37.9576589, "lon": -8.8633209}, {"type": "node", "id": 2689090912, "lat": 37.9576326, "lon": -8.863333}, {"type": "node", "id": 2689090915, "lat": 37.9576074, "lon": -8.8633387}, {"type": "node", "id": 2689090918, "lat": 37.9575861, "lon": -8.8633337}, {"type": "node", "id": 2689090922, "lat": 37.9575548, "lon": -8.8633068}, {"type": "node", "id": 2689090926, "lat": 37.9575392, "lon": -8.8632819}, {"type": "node", "id": 2689090929, "lat": 37.9575313, "lon": -8.8632358}, {"type": "node", "id": 2689090932, "lat": 37.9575296, "lon": -8.8631996}, {"type": "node", "id": 2689090935, "lat": 37.9575341, "lon": -8.8631705}, {"type": "node", "id": 2689090938, "lat": 37.9575397, "lon": -8.8631514}, {"type": "node", "id": 2689090942, "lat": 37.9575447, "lon": -8.8631365}, {"type": "node", "id": 2689090944, "lat": 37.9575755, "lon": -8.8630443}, {"type": "node", "id": 2689090946, "lat": 37.9575845, "lon": -8.8630329}, {"type": "node", "id": 2689090949, "lat": 37.9575962, "lon": -8.8630272}, {"type": "node", "id": 2689090951, "lat": 37.9577618, "lon": -8.8630003}, {"type": "node", "id": 2689090953, "lat": 37.9577763, "lon": -8.8630052}, {"type": "node", "id": 2689090955, "lat": 37.9577819, "lon": -8.8630237}, {"type": "node", "id": 2689090957, "lat": 37.9573276, "lon": -8.8628001}, {"type": "node", "id": 2689090959, "lat": 37.9573433, "lon": -8.8627503}, {"type": "node", "id": 2689090961, "lat": 37.9573548, "lon": -8.8627503}, {"type": "node", "id": 2689090963, "lat": 37.9577498, "lon": -8.8629288}, {"type": "node", "id": 2689090964, "lat": 37.9577721, "lon": -8.8629533}, {"type": "node", "id": 2689090967, "lat": 37.9577775, "lon": -8.862964}, {"type": "node", "id": 2689090969, "lat": 37.957574, "lon": -8.8630061}, {"type": "node", "id": 2689090971, "lat": 37.9575656, "lon": -8.8629993}, {"type": "node", "id": 2689090973, "lat": 37.9575426, "lon": -8.8629456}, {"type": "node", "id": 2689090975, "lat": 37.9575547, "lon": -8.8629204}, {"type": "node", "id": 2689090977, "lat": 37.9575003, "lon": -8.8628736}, {"type": "node", "id": 2689090980, "lat": 37.957542, "lon": -8.8628912}, {"type": "node", "id": 2689139547, "lat": 37.9558584, "lon": -8.8725726}, {"type": "node", "id": 2689139548, "lat": 37.9559234, "lon": -8.8725623}, {"type": "node", "id": 2689139549, "lat": 37.9559166, "lon": -8.8724776}, {"type": "node", "id": 2689139550, "lat": 37.9558494, "lon": -8.8724851}, {"type": "node", "id": 2697017826, "lat": 37.958526, "lon": -8.8658041}, {"type": "node", "id": 2697017827, "lat": 37.9586404, "lon": -8.8658466}, {"type": "node", "id": 2697017828, "lat": 37.9586092, "lon": -8.865977}, {"type": "node", "id": 2697017829, "lat": 37.9584959, "lon": -8.865933}, {"type": "node", "id": 2697037949, "lat": 37.9619209, "lon": -8.8573768}, {"type": "node", "id": 2697037950, "lat": 37.9622113, "lon": -8.8570604}, {"type": "node", "id": 2697037951, "lat": 37.9622552, "lon": -8.8571348}, {"type": "node", "id": 2697037952, "lat": 37.9622899, "lon": -8.8571362}, {"type": "node", "id": 2697037953, "lat": 37.9624753, "lon": -8.8572195}, {"type": "node", "id": 2697037954, "lat": 37.9625822, "lon": -8.8573584}, {"type": "node", "id": 2697037955, "lat": 37.9621862, "lon": -8.8577803}, {"type": "node", "id": 2697037957, "lat": 37.9622742, "lon": -8.8571149}, {"type": "node", "id": 2697037959, "lat": 37.9620503, "lon": -8.8575737}, {"type": "node", "id": 2697037960, "lat": 37.9624089, "lon": -8.8571896}, {"type": "node", "id": 2697037962, "lat": 37.9619759, "lon": -8.8573169}, {"type": "node", "id": 2697037964, "lat": 37.9620386, "lon": -8.8574136}, {"type": "node", "id": 2697037966, "lat": 37.9621473, "lon": -8.8572999}, {"type": "node", "id": 2697037968, "lat": 37.9620836, "lon": -8.8571995}, {"type": "node", "id": 2697037970, "lat": 37.9620701, "lon": -8.8575527}, {"type": "node", "id": 2697037971, "lat": 37.9621901, "lon": -8.8577332}, {"type": "node", "id": 2697037973, "lat": 37.9624985, "lon": -8.8574094}, {"type": "node", "id": 2697037975, "lat": 37.9623785, "lon": -8.8572236}, {"type": "node", "id": 2697037979, "lat": 37.9622641, "lon": -8.8573457}, {"type": "node", "id": 2697067682, "lat": 37.9555419, "lon": -8.8615089}, {"type": "node", "id": 2697067683, "lat": 37.955254, "lon": -8.8617192}, {"type": "node", "id": 2697067685, "lat": 37.9554554, "lon": -8.8613262}, {"type": "node", "id": 2697067686, "lat": 37.9553728, "lon": -8.8611469}, {"type": "node", "id": 2697067688, "lat": 37.9550855, "lon": -8.8613516}, {"type": "node", "id": 2697067689, "lat": 37.9551701, "lon": -8.8615309}, {"type": "node", "id": 2697067691, "lat": 37.9553628, "lon": -8.8631642}, {"type": "node", "id": 2697067692, "lat": 37.9555222, "lon": -8.8631159}, {"type": "node", "id": 2697067693, "lat": 37.9555037, "lon": -8.8630155}, {"type": "node", "id": 2697067695, "lat": 37.9553432, "lon": -8.8630611}, {"type": "node", "id": 2697067696, "lat": 37.9555588, "lon": -8.8629664}, {"type": "node", "id": 2697067697, "lat": 37.95553, "lon": -8.8627994}, {"type": "node", "id": 2697067699, "lat": 37.955275, "lon": -8.8628698}, {"type": "node", "id": 2697067700, "lat": 37.9553058, "lon": -8.8630381}, {"type": "node", "id": 2702090551, "lat": 37.9588769, "lon": -8.863231}, {"type": "node", "id": 2702090552, "lat": 37.9586196, "lon": -8.863135}, {"type": "node", "id": 2702090553, "lat": 37.9586268, "lon": -8.8631076}, {"type": "node", "id": 2702090554, "lat": 37.9586466, "lon": -8.8630671}, {"type": "node", "id": 2702090555, "lat": 37.9587258, "lon": -8.8629129}, {"type": "node", "id": 2702090556, "lat": 37.9588249, "lon": -8.8624811}, {"type": "node", "id": 2702090557, "lat": 37.9588444, "lon": -8.862444}, {"type": "node", "id": 2702090558, "lat": 37.9588639, "lon": -8.8624227}, {"type": "node", "id": 2702090559, "lat": 37.9588829, "lon": -8.8624077}, {"type": "node", "id": 2702090560, "lat": 37.9589066, "lon": -8.8623961}, {"type": "node", "id": 2702090561, "lat": 37.9589291, "lon": -8.8623969}, {"type": "node", "id": 2702090562, "lat": 37.9589467, "lon": -8.862403}, {"type": "node", "id": 2702090563, "lat": 37.9589716, "lon": -8.8624223}, {"type": "node", "id": 2702090564, "lat": 37.9589838, "lon": -8.8624416}, {"type": "node", "id": 2702090565, "lat": 37.9589947, "lon": -8.8624716}, {"type": "node", "id": 2702090566, "lat": 37.9590008, "lon": -8.8624962}, {"type": "node", "id": 2702090567, "lat": 37.9590001, "lon": -8.8625355}, {"type": "node", "id": 2702090568, "lat": 37.9589613, "lon": -8.8626973}, {"type": "node", "id": 2702090569, "lat": 37.9589005, "lon": -8.8629445}, {"type": "node", "id": 2707858717, "lat": 37.957678, "lon": -8.8651142}, {"type": "node", "id": 2707858718, "lat": 37.9575619, "lon": -8.8650112}, {"type": "node", "id": 2707858719, "lat": 37.9574662, "lon": -8.8650128}, {"type": "node", "id": 2707858720, "lat": 37.9574682, "lon": -8.8651113}, {"type": "node", "id": 2707967440, "lat": 37.9570788, "lon": -8.8644065}, {"type": "node", "id": 2707967441, "lat": 37.957136, "lon": -8.8644207}, {"type": "node", "id": 2707967442, "lat": 37.95721, "lon": -8.8643813}, {"type": "node", "id": 2707967447, "lat": 37.9568611, "lon": -8.8636982}, {"type": "node", "id": 2707967448, "lat": 37.9567131, "lon": -8.8639657}, {"type": "node", "id": 2707967449, "lat": 37.9567178, "lon": -8.8640477}, {"type": "node", "id": 2707967450, "lat": 37.956749, "lon": -8.8641039}, {"type": "node", "id": 2707967451, "lat": 37.9570188, "lon": -8.8642783}, {"type": "node", "id": 2710131716, "lat": 37.9582776, "lon": -8.8691229}, {"type": "node", "id": 2954468904, "lat": 37.9555813, "lon": -8.8529674}, {"type": "node", "id": 2954468905, "lat": 37.9556177, "lon": -8.8528371}, {"type": "node", "id": 2954468906, "lat": 37.9555025, "lon": -8.8534114}, {"type": "node", "id": 2954468910, "lat": 37.9555538, "lon": -8.852865}, {"type": "node", "id": 2954468911, "lat": 37.9553306, "lon": -8.8525668}, {"type": "node", "id": 2954468912, "lat": 37.9550446, "lon": -8.8526767}, {"type": "node", "id": 2954468913, "lat": 37.9555257, "lon": -8.853256}, {"type": "node", "id": 2954468914, "lat": 37.9552062, "lon": -8.8533177}, {"type": "node", "id": 2954468915, "lat": 37.9554585, "lon": -8.8525229}, {"type": "node", "id": 2954468917, "lat": 37.9555005, "lon": -8.8526227}, {"type": "node", "id": 2954468918, "lat": 37.9554285, "lon": -8.8532183}, {"type": "node", "id": 2954468919, "lat": 37.9555491, "lon": -8.8525989}, {"type": "node", "id": 2954468921, "lat": 37.9555026, "lon": -8.8529981}, {"type": "node", "id": 2955899333, "lat": 37.9734811, "lon": -8.8435544}, {"type": "node", "id": 2955899334, "lat": 37.9730011, "lon": -8.8443295}, {"type": "node", "id": 2955899335, "lat": 37.9730286, "lon": -8.8442196}, {"type": "node", "id": 2955899336, "lat": 37.9735551, "lon": -8.8455607}, {"type": "node", "id": 2955899337, "lat": 37.9727516, "lon": -8.8447802}, {"type": "node", "id": 2955899338, "lat": 37.9738088, "lon": -8.8454722}, {"type": "node", "id": 2955899339, "lat": 37.9743268, "lon": -8.845794}, {"type": "node", "id": 2955899340, "lat": 37.9742697, "lon": -8.8458048}, {"type": "node", "id": 2955899341, "lat": 37.9733458, "lon": -8.844182}, {"type": "node", "id": 2955899342, "lat": 37.9728552, "lon": -8.8448901}, {"type": "node", "id": 2955899343, "lat": 37.9735572, "lon": -8.8435517}, {"type": "node", "id": 2955899344, "lat": 37.9731026, "lon": -8.8452013}, {"type": "node", "id": 2955899345, "lat": 37.9728277, "lon": -8.8442813}, {"type": "node", "id": 2955899348, "lat": 37.9732697, "lon": -8.8448231}, {"type": "node", "id": 2955899349, "lat": 37.9728531, "lon": -8.8440908}, {"type": "node", "id": 2955899351, "lat": 37.9735234, "lon": -8.8440586}, {"type": "node", "id": 2955899352, "lat": 37.9730286, "lon": -8.8445844}, {"type": "node", "id": 2955899353, "lat": 37.9735001, "lon": -8.8437261}, {"type": "node", "id": 2955899355, "lat": 37.9737073, "lon": -8.8458584}, {"type": "node", "id": 2955899356, "lat": 37.9735361, "lon": -8.8436858}, {"type": "node", "id": 2955899357, "lat": 37.972536, "lon": -8.8448016}, {"type": "node", "id": 2955899358, "lat": 37.9743755, "lon": -8.8458289}, {"type": "node", "id": 2955899359, "lat": 37.9739272, "lon": -8.8457377}, {"type": "node", "id": 2955899360, "lat": 37.9740097, "lon": -8.8452791}, {"type": "node", "id": 2955899361, "lat": 37.9729504, "lon": -8.8442866}, {"type": "node", "id": 2955899362, "lat": 37.9729335, "lon": -8.84441}, {"type": "node", "id": 2955899363, "lat": 37.9735805, "lon": -8.8451369}, {"type": "node", "id": 2955899364, "lat": 37.9729335, "lon": -8.8439889}, {"type": "node", "id": 2955899365, "lat": 37.9730899, "lon": -8.8445066}, {"type": "node", "id": 2955899367, "lat": 37.9740435, "lon": -8.845727}, {"type": "node", "id": 2955899368, "lat": 37.9741556, "lon": -8.8463573}, {"type": "node", "id": 2955899369, "lat": 37.9730476, "lon": -8.8439084}, {"type": "node", "id": 2955899370, "lat": 37.9736883, "lon": -8.8453434}, {"type": "node", "id": 2955899373, "lat": 37.9740625, "lon": -8.8453273}, {"type": "node", "id": 2955899374, "lat": 37.9745277, "lon": -8.8462125}, {"type": "node", "id": 2955899376, "lat": 37.9730794, "lon": -8.8447131}, {"type": "node", "id": 2955899377, "lat": 37.9734769, "lon": -8.8437877}, {"type": "node", "id": 2955899378, "lat": 37.9733458, "lon": -8.8453542}, {"type": "node", "id": 2955899380, "lat": 37.9729736, "lon": -8.8442035}, {"type": "node", "id": 2955899381, "lat": 37.9734874, "lon": -8.8450859}, {"type": "node", "id": 2955899382, "lat": 37.9744452, "lon": -8.8463439}, {"type": "node", "id": 2955899383, "lat": 37.9730878, "lon": -8.8441445}, {"type": "node", "id": 2955899384, "lat": 37.9731238, "lon": -8.845389}, {"type": "node", "id": 2955899387, "lat": 37.9733267, "lon": -8.8449304}, {"type": "node", "id": 2955899388, "lat": 37.9730498, "lon": -8.8448499}, {"type": "node", "id": 2955899389, "lat": 37.9732781, "lon": -8.8440667}, {"type": "node", "id": 2955899390, "lat": 37.9730392, "lon": -8.8446568}, {"type": "node", "id": 2955899391, "lat": 37.9743332, "lon": -8.8462902}, {"type": "node", "id": 2955899392, "lat": 37.9731301, "lon": -8.8440399}, {"type": "node", "id": 2955899393, "lat": 37.9727347, "lon": -8.8449921}, {"type": "node", "id": 2955899394, "lat": 37.9740076, "lon": -8.8455419}, {"type": "node", "id": 2955899395, "lat": 37.9742105, "lon": -8.8459013}, {"type": "node", "id": 2955899396, "lat": 37.9741535, "lon": -8.8455553}, {"type": "node", "id": 2955899397, "lat": 37.9725761, "lon": -8.8446943}, {"type": "node", "id": 2955899398, "lat": 37.9733331, "lon": -8.8437958}, {"type": "node", "id": 2955899400, "lat": 37.9737623, "lon": -8.8453515}, {"type": "node", "id": 2955899401, "lat": 37.9735932, "lon": -8.8456921}, {"type": "node", "id": 2955899402, "lat": 37.9741852, "lon": -8.8465182}, {"type": "node", "id": 2955899403, "lat": 37.9745531, "lon": -8.8460623}, {"type": "node", "id": 2955899404, "lat": 37.9731787, "lon": -8.8447614}, {"type": "node", "id": 2955899405, "lat": 37.9728341, "lon": -8.8447319}, {"type": "node", "id": 2955899406, "lat": 37.9735889, "lon": -8.8452335}, {"type": "node", "id": 2955899408, "lat": 37.9728256, "lon": -8.8444958}, {"type": "node", "id": 2955899409, "lat": 37.9730286, "lon": -8.8450323}, {"type": "node", "id": 2955899410, "lat": 37.9730582, "lon": -8.8445093}, {"type": "node", "id": 2955899411, "lat": 37.9741704, "lon": -8.8453246}, {"type": "node", "id": 2955899412, "lat": 37.9734388, "lon": -8.8441311}, {"type": "node", "id": 2955899413, "lat": 37.9741704, "lon": -8.8454346}, {"type": "node", "id": 2955899415, "lat": 37.9741217, "lon": -8.8464619}, {"type": "node", "id": 2955899416, "lat": 37.9736798, "lon": -8.8437261}, {"type": "node", "id": 2955899418, "lat": 37.9739653, "lon": -8.8460783}, {"type": "node", "id": 2955899419, "lat": 37.9734747, "lon": -8.8438414}, {"type": "node", "id": 2955899421, "lat": 37.9729292, "lon": -8.8445119}, {"type": "node", "id": 2955899422, "lat": 37.973405, "lon": -8.8450189}, {"type": "node", "id": 2955899423, "lat": 37.9734134, "lon": -8.8436054}, {"type": "node", "id": 2955899424, "lat": 37.973202, "lon": -8.8442357}, {"type": "node", "id": 2955899425, "lat": 37.9733648, "lon": -8.8437019}, {"type": "node", "id": 2955899426, "lat": 37.97298, "lon": -8.8448633}, {"type": "node", "id": 2955899428, "lat": 37.9738236, "lon": -8.8458477}, {"type": "node", "id": 2955899429, "lat": 37.9736037, "lon": -8.8454185}, {"type": "node", "id": 2955899431, "lat": 37.97409, "lon": -8.8451986}, {"type": "node", "id": 2955899434, "lat": 37.9732866, "lon": -8.843997}, {"type": "node", "id": 2955899435, "lat": 37.9744452, "lon": -8.8460757}, {"type": "node", "id": 2955899436, "lat": 37.9741112, "lon": -8.8456519}, {"type": "node", "id": 2955899437, "lat": 37.9731576, "lon": -8.8443269}, {"type": "node", "id": 2955899440, "lat": 37.9733965, "lon": -8.8439487}, {"type": "node", "id": 2955899441, "lat": 37.9727136, "lon": -8.8446192}, {"type": "node", "id": 2955899442, "lat": 37.973128, "lon": -8.8451074}, {"type": "node", "id": 2955899443, "lat": 37.9730371, "lon": -8.8444583}, {"type": "node", "id": 2955899444, "lat": 37.9736397, "lon": -8.8455553}, {"type": "node", "id": 2955899445, "lat": 37.9729927, "lon": -8.8451128}, {"type": "node", "id": 2955899446, "lat": 37.9738659, "lon": -8.8455634}, {"type": "node", "id": 2955899447, "lat": 37.9737221, "lon": -8.8455553}, {"type": "node", "id": 2955899448, "lat": 37.9736629, "lon": -8.8451718}, {"type": "node", "id": 2955899449, "lat": 37.9729758, "lon": -8.8446943}, {"type": "node", "id": 2955899450, "lat": 37.9741048, "lon": -8.8457618}, {"type": "node", "id": 2955899451, "lat": 37.9725719, "lon": -8.8449465}, {"type": "node", "id": 2955899452, "lat": 37.9732147, "lon": -8.8452817}, {"type": "node", "id": 2955899453, "lat": 37.9743163, "lon": -8.8464834}, {"type": "node", "id": 2955899454, "lat": 37.973553, "lon": -8.8438655}, {"type": "node", "id": 2955899457, "lat": 37.9728003, "lon": -8.844579}, {"type": "node", "id": 2955899458, "lat": 37.9729102, "lon": -8.8450242}, {"type": "node", "id": 2955899459, "lat": 37.9729821, "lon": -8.8445173}, {"type": "node", "id": 2955899461, "lat": 37.9740308, "lon": -8.8460757}, {"type": "node", "id": 2955899462, "lat": 37.9729673, "lon": -8.8449599}, {"type": "node", "id": 2955899463, "lat": 37.9736439, "lon": -8.845786}, {"type": "node", "id": 2955899464, "lat": 37.9732041, "lon": -8.8444449}, {"type": "node", "id": 2955899466, "lat": 37.973591, "lon": -8.8438146}, {"type": "node", "id": 2955899467, "lat": 37.9744241, "lon": -8.8461856}, {"type": "node", "id": 2955899468, "lat": 37.9741239, "lon": -8.8460113}, {"type": "node", "id": 2955899469, "lat": 37.9736735, "lon": -8.8438655}, {"type": "node", "id": 2955899471, "lat": 37.9744622, "lon": -8.8457618}, {"type": "node", "id": 2955899472, "lat": 37.9736524, "lon": -8.8436161}, {"type": "node", "id": 2955899474, "lat": 37.9740647, "lon": -8.8454293}, {"type": "node", "id": 2955899476, "lat": 37.9737708, "lon": -8.8456438}, {"type": "node", "id": 2955899477, "lat": 37.972887, "lon": -8.8447775}, {"type": "node", "id": 2955899478, "lat": 37.9732929, "lon": -8.8438092}, {"type": "node", "id": 2955899479, "lat": 37.9739441, "lon": -8.8455929}, {"type": "node", "id": 2955899480, "lat": 37.9737052, "lon": -8.8454373}, {"type": "node", "id": 2955899481, "lat": 37.9739357, "lon": -8.8458799}, {"type": "node", "id": 2955899482, "lat": 37.9743459, "lon": -8.8456465}, {"type": "node", "id": 2955899483, "lat": 37.9730117, "lon": -8.8441016}, {"type": "node", "id": 2955899484, "lat": 37.9737496, "lon": -8.8457592}, {"type": "node", "id": 2955899485, "lat": 37.9740181, "lon": -8.8458584}, {"type": "node", "id": 2955899486, "lat": 37.9744178, "lon": -8.8459335}, {"type": "node", "id": 2955899487, "lat": 37.9729187, "lon": -8.8446192}, {"type": "node", "id": 2955899488, "lat": 37.9735234, "lon": -8.8454668}, {"type": "node", "id": 2955899489, "lat": 37.973479, "lon": -8.8454293}, {"type": "node", "id": 2955899490, "lat": 37.9736249, "lon": -8.8439514}, {"type": "node", "id": 2955899491, "lat": 37.9741556, "lon": -8.8452522}, {"type": "node", "id": 2955899492, "lat": 37.9736397, "lon": -8.8452737}, {"type": "node", "id": 2955899493, "lat": 37.973682, "lon": -8.8456894}, {"type": "node", "id": 2955899495, "lat": 37.9731639, "lon": -8.8443912}, {"type": "node", "id": 2955899496, "lat": 37.9733098, "lon": -8.8452254}, {"type": "node", "id": 2955899497, "lat": 37.9738701, "lon": -8.8460113}, {"type": "node", "id": 2955899501, "lat": 37.9737116, "lon": -8.8452335}, {"type": "node", "id": 2955899503, "lat": 37.9726967, "lon": -8.8448365}, {"type": "node", "id": 2955899504, "lat": 37.9726819, "lon": -8.8449009}, {"type": "node", "id": 2955899506, "lat": 37.9726501, "lon": -8.8446407}, {"type": "node", "id": 2955899507, "lat": 37.9735551, "lon": -8.8453515}, {"type": "node", "id": 2955899508, "lat": 37.9737898, "lon": -8.8459684}, {"type": "node", "id": 2955899510, "lat": 37.9735974, "lon": -8.8437556}, {"type": "node", "id": 2955899511, "lat": 37.9734071, "lon": -8.8440023}, {"type": "node", "id": 2955899512, "lat": 37.97409, "lon": -8.8463278}, {"type": "node", "id": 2955899513, "lat": 37.9733733, "lon": -8.8457484}, {"type": "node", "id": 2955899514, "lat": 37.9735762, "lon": -8.84371}, {"type": "node", "id": 2955899516, "lat": 37.974534, "lon": -8.8458906}, {"type": "node", "id": 2955899517, "lat": 37.9742528, "lon": -8.8463546}, {"type": "node", "id": 2955899518, "lat": 37.974238, "lon": -8.8456546}, {"type": "node", "id": 4632423370, "lat": 37.9580391, "lon": -8.8692737}, {"type": "node", "id": 4632423371, "lat": 37.9584117, "lon": -8.8682701}, {"type": "node", "id": 4632423372, "lat": 37.958334, "lon": -8.868233}, {"type": "node", "id": 4632423373, "lat": 37.9583771, "lon": -8.8680095}, {"type": "node", "id": 4632423374, "lat": 37.9577475, "lon": -8.8677966}, {"type": "node", "id": 4632423375, "lat": 37.957452, "lon": -8.8688987}, {"type": "node", "id": 4632472985, "lat": 37.9579854, "lon": -8.8693163}, {"type": "node", "id": 4640750103, "lat": 37.9577835, "lon": -8.8677818}, {"type": "node", "id": 4640750104, "lat": 37.9579765, "lon": -8.8678402, "tags": {"highway": "crossing"}}, {"type": "node", "id": 4640750105, "lat": 37.9574812, "lon": -8.8689536}, {"type": "node", "id": 4640750106, "lat": 37.9575321, "lon": -8.8690147}, {"type": "node", "id": 4640750107, "lat": 37.9574601, "lon": -8.868765}, {"type": "node", "id": 4640750108, "lat": 37.957546, "lon": -8.8684292}, {"type": "node", "id": 4640750109, "lat": 37.95763, "lon": -8.868096}, {"type": "node", "id": 4640750110, "lat": 37.9576666, "lon": -8.8679609}, {"type": "node", "id": 5032006567, "lat": 37.9553431, "lon": -8.8667704}, {"type": "node", "id": 5041868653, "lat": 37.9568113, "lon": -8.8637795}, {"type": "node", "id": 5041868685, "lat": 37.9571003, "lon": -8.8637487}, {"type": "node", "id": 5041868926, "lat": 37.9571515, "lon": -8.8637647}, {"type": "node", "id": 5256790932, "lat": 37.9557746, "lon": -8.872709}, {"type": "node", "id": 5256790933, "lat": 37.9557247, "lon": -8.8719893}, {"type": "node", "id": 5256790934, "lat": 37.9561455, "lon": -8.8719577}, {"type": "node", "id": 5256790936, "lat": 37.9558854, "lon": -8.8726973}, {"type": "node", "id": 5256790938, "lat": 37.9557511, "lon": -8.872388}, {"type": "node", "id": 5256790939, "lat": 37.955849, "lon": -8.8728074}, {"type": "node", "id": 5256790940, "lat": 37.9557859, "lon": -8.8728583}, {"type": "node", "id": 5256816146, "lat": 37.9586137, "lon": -8.8651299}, {"type": "node", "id": 5256816151, "lat": 37.9588695, "lon": -8.8649097}, {"type": "node", "id": 5256816339, "lat": 37.9552023, "lon": -8.8642808}, {"type": "node", "id": 5256816344, "lat": 37.9558831, "lon": -8.8634034}, {"type": "node", "id": 5256816345, "lat": 37.9560242, "lon": -8.8640037}, {"type": "node", "id": 5256816346, "lat": 37.956028, "lon": -8.8643177}, {"type": "node", "id": 5256816347, "lat": 37.9555706, "lon": -8.8642895}, {"type": "node", "id": 5257551346, "lat": 37.9580339, "lon": -8.8678471}, {"type": "node", "id": 5257551347, "lat": 37.958353, "lon": -8.8685064}, {"type": "node", "id": 5257551348, "lat": 37.9583834, "lon": -8.8683586}, {"type": "node", "id": 5260518310, "lat": 37.9585095, "lon": -8.8655613}, {"type": "node", "id": 5260518311, "lat": 37.958779, "lon": -8.864875}, {"type": "node", "id": 5260518312, "lat": 37.9588398, "lon": -8.8648984}, {"type": "node", "id": 5260518313, "lat": 37.9589883, "lon": -8.864419}, {"type": "node", "id": 5260518314, "lat": 37.959018, "lon": -8.8642871}, {"type": "node", "id": 5260518315, "lat": 37.9593253, "lon": -8.8646006}, {"type": "node", "id": 5260518316, "lat": 37.9589849, "lon": -8.8660146}, {"type": "node", "id": 5260518318, "lat": 37.9585066, "lon": -8.8655734}, {"type": "node", "id": 5260520527, "lat": 37.9587659, "lon": -8.8665749}, {"type": "node", "id": 5262641058, "lat": 37.958221, "lon": -8.8663558}, {"type": "node", "id": 5262683054, "lat": 37.9573184, "lon": -8.8641441, "tags": {"highway": "crossing"}}, {"type": "node", "id": 5262683058, "lat": 37.9568882, "lon": -8.8641977}, {"type": "node", "id": 5262683059, "lat": 37.9567698, "lon": -8.8641375}, {"type": "node", "id": 5262683060, "lat": 37.9566973, "lon": -8.8639976}, {"type": "node", "id": 5262690970, "lat": 37.9580508, "lon": -8.8711454}, {"type": "node", "id": 5262690971, "lat": 37.9575905, "lon": -8.8709008}, {"type": "node", "id": 5262690972, "lat": 37.9579387, "lon": -8.8698465}, {"type": "node", "id": 5262690974, "lat": 37.9578404, "lon": -8.8700236}, {"type": "node", "id": 5262690975, "lat": 37.9577878, "lon": -8.8699419}, {"type": "node", "id": 5262690976, "lat": 37.9577601, "lon": -8.8699244}, {"type": "node", "id": 5262690977, "lat": 37.9578444, "lon": -8.8696931}, {"type": "node", "id": 5262690980, "lat": 37.9579558, "lon": -8.8698556}, {"type": "node", "id": 5262690981, "lat": 37.9578738, "lon": -8.8700431}, {"type": "node", "id": 5262690983, "lat": 37.9580795, "lon": -8.8695305}, {"type": "node", "id": 5263953744, "lat": 37.9591592, "lon": -8.863636}, {"type": "node", "id": 5264746695, "lat": 37.958197, "lon": -8.8689478}, {"type": "node", "id": 5264746696, "lat": 37.9582125, "lon": -8.8688934}, {"type": "node", "id": 5264746708, "lat": 37.9583158, "lon": -8.8690186}, {"type": "node", "id": 5264755441, "lat": 37.9562623, "lon": -8.8564864}, {"type": "node", "id": 5264755442, "lat": 37.9561878, "lon": -8.8565191}, {"type": "node", "id": 5264755443, "lat": 37.956163, "lon": -8.8564145}, {"type": "node", "id": 5264755444, "lat": 37.9562377, "lon": -8.856385}, {"type": "node", "id": 5264764588, "lat": 37.955531, "lon": -8.8531205}, {"type": "node", "id": 5284944278, "lat": 37.9591345, "lon": -8.8722755}, {"type": "node", "id": 5284944279, "lat": 37.9585249, "lon": -8.869726}, {"type": "node", "id": 5284944280, "lat": 37.9587148, "lon": -8.8698215}, {"type": "node", "id": 5284944281, "lat": 37.958788, "lon": -8.86985}, {"type": "node", "id": 5284944282, "lat": 37.9588912, "lon": -8.8698898}, {"type": "node", "id": 5284944283, "lat": 37.9589231, "lon": -8.8698991}, {"type": "node", "id": 5284944284, "lat": 37.9590946, "lon": -8.8699486}, {"type": "node", "id": 5284944285, "lat": 37.9593563, "lon": -8.8700339}, {"type": "node", "id": 5284944286, "lat": 37.9595806, "lon": -8.8700832}, {"type": "node", "id": 5284944287, "lat": 37.9596927, "lon": -8.8701098}, {"type": "node", "id": 5284944288, "lat": 37.9597884, "lon": -8.8701344}, {"type": "node", "id": 5284944289, "lat": 37.9598653, "lon": -8.870154}, {"type": "node", "id": 5284945735, "lat": 37.9584857, "lon": -8.8697872}, {"type": "node", "id": 5284945736, "lat": 37.9583643, "lon": -8.8701028}, {"type": "node", "id": 5284945737, "lat": 37.958399, "lon": -8.870091}, {"type": "node", "id": 5297380455, "lat": 37.9572077, "lon": -8.8610557, "tags": {"leisure": "playground", "name": "Parque Infantil Bairro 1\u00ba Maio"}}, {"type": "node", "id": 5301603124, "lat": 37.95769, "lon": -8.8678864}, {"type": "node", "id": 5301606922, "lat": 37.9566664, "lon": -8.8600078}, {"type": "node", "id": 5301606926, "lat": 37.9565429, "lon": -8.8599471}, {"type": "node", "id": 5301612231, "lat": 37.9553879, "lon": -8.8637932}, {"type": "node", "id": 5301612232, "lat": 37.9552616, "lon": -8.8638887}, {"type": "node", "id": 5301612233, "lat": 37.9552154, "lon": -8.8637303}, {"type": "node", "id": 5301612234, "lat": 37.9550168, "lon": -8.8639178}, {"type": "node", "id": 5301612236, "lat": 37.9549889, "lon": -8.8640453}, {"type": "node", "id": 5302702875, "lat": 37.9586415, "lon": -8.8650067}, {"type": "node", "id": 5302702876, "lat": 37.9591404, "lon": -8.8637177}, {"type": "node", "id": 5302702877, "lat": 37.9591928, "lon": -8.8634902}, {"type": "node", "id": 5302704691, "lat": 37.9590899, "lon": -8.86393}, {"type": "node", "id": 5302709108, "lat": 37.9555518, "lon": -8.8529789}, {"type": "node", "id": 5303837395, "lat": 37.9618281, "lon": -8.8682246}, {"type": "node", "id": 5303842117, "lat": 37.9580576, "lon": -8.8692243}, {"type": "node", "id": 5303842118, "lat": 37.958071, "lon": -8.8691887}, {"type": "node", "id": 5305605971, "lat": 37.955932, "lon": -8.8727188}, {"type": "node", "id": 5309598818, "lat": 37.9606305, "lon": -8.8691699}, {"type": "node", "id": 5309598819, "lat": 37.9608933, "lon": -8.869307}, {"type": "node", "id": 5309598820, "lat": 37.9609914, "lon": -8.8690043}, {"type": "node", "id": 5309600521, "lat": 37.9607286, "lon": -8.8688672}, {"type": "node", "id": 5309600522, "lat": 37.9608141, "lon": -8.8692464}, {"type": "node", "id": 5309600523, "lat": 37.9608405, "lon": -8.8691547}, {"type": "node", "id": 5309600524, "lat": 37.9609191, "lon": -8.8691922}, {"type": "node", "id": 5309600525, "lat": 37.9608883, "lon": -8.8692863}, {"type": "node", "id": 5319303241, "lat": 37.9578938, "lon": -8.8692596}, {"type": "node", "id": 5319303251, "lat": 37.9580051, "lon": -8.8678476}, {"type": "node", "id": 5332241346, "lat": 37.9575855, "lon": -8.86907}, {"type": "node", "id": 5333385239, "lat": 37.955398, "lon": -8.8642892}, {"type": "node", "id": 5333385243, "lat": 37.9560301, "lon": -8.8642157}, {"type": "node", "id": 5333385247, "lat": 37.9559753, "lon": -8.8637813}, {"type": "node", "id": 5349965148, "lat": 37.9570019, "lon": -8.8612798}, {"type": "node", "id": 5349965149, "lat": 37.9572575, "lon": -8.8613966}, {"type": "node", "id": 5349965150, "lat": 37.9573985, "lon": -8.8609006}, {"type": "node", "id": 5365093291, "lat": 37.9576773, "lon": -8.8650086}, {"type": "node", "id": 5367245023, "lat": 37.958407, "lon": -8.8682908}, {"type": "node", "id": 5431893860, "lat": 37.9575251, "lon": -8.868511}, {"type": "node", "id": 5444096908, "lat": 37.9549961, "lon": -8.8639964}, {"type": "node", "id": 5444096909, "lat": 37.9550685, "lon": -8.8638044}, {"type": "node", "id": 5444096910, "lat": 37.9550359, "lon": -8.8638573}, {"type": "node", "id": 5444096911, "lat": 37.9550507, "lon": -8.8638299}, {"type": "node", "id": 5444096912, "lat": 37.9550778, "lon": -8.8637968}, {"type": "node", "id": 5452305740, "lat": 37.9583684, "lon": -8.8680982}, {"type": "node", "id": 5491415764, "lat": 37.959017, "lon": -8.8658793, "tags": {"highway": "crossing"}}, {"type": "node", "id": 5491415784, "lat": 37.9599081, "lon": -8.8575902}, {"type": "node", "id": 5491415785, "lat": 37.9599506, "lon": -8.8574482}, {"type": "node", "id": 5491415786, "lat": 37.9601399, "lon": -8.8575393}, {"type": "node", "id": 5491415789, "lat": 37.9601769, "lon": -8.8575501}, {"type": "node", "id": 5491415790, "lat": 37.9603662, "lon": -8.8576413}, {"type": "node", "id": 5491415792, "lat": 37.9603283, "lon": -8.8573867}, {"type": "node", "id": 5491415795, "lat": 37.96049, "lon": -8.8574675}, {"type": "node", "id": 5491415796, "lat": 37.9601058, "lon": -8.8572831}, {"type": "node", "id": 5491415799, "lat": 37.9602951, "lon": -8.8573743}, {"type": "node", "id": 5491415800, "lat": 37.9598123, "lon": -8.8572192}, {"type": "node", "id": 5491415803, "lat": 37.9599673, "lon": -8.8572969}, {"type": "node", "id": 5491415816, "lat": 37.9589412, "lon": -8.8568848}, {"type": "node", "id": 5491415817, "lat": 37.9591019, "lon": -8.8569613}, {"type": "node", "id": 5491415818, "lat": 37.9593396, "lon": -8.8569196}, {"type": "node", "id": 5491415820, "lat": 37.9591368, "lon": -8.8569854}, {"type": "node", "id": 5491415921, "lat": 37.9592975, "lon": -8.8570619}, {"type": "node", "id": 5491415923, "lat": 37.9596372, "lon": -8.8569828}, {"type": "node", "id": 5491415924, "lat": 37.9595947, "lon": -8.8571249}, {"type": "node", "id": 5491415925, "lat": 37.9597839, "lon": -8.8572161}, {"type": "node", "id": 5491415926, "lat": 37.9594776, "lon": -8.8572231}, {"type": "node", "id": 5491415927, "lat": 37.9596689, "lon": -8.8573143}, {"type": "node", "id": 5491415928, "lat": 37.9596253, "lon": -8.8574615}, {"type": "node", "id": 5491415930, "lat": 37.9594543, "lon": -8.8572168}, {"type": "node", "id": 5491415931, "lat": 37.9592661, "lon": -8.8571229}, {"type": "node", "id": 5491415932, "lat": 37.9592235, "lon": -8.8572603}, {"type": "node", "id": 5533727699, "lat": 37.9568806, "lon": -8.8533702, "tags": {"denotation": "natural_monument", "leisure": "playground", "natural": "tree", "surface": "grass"}}, {"type": "node", "id": 5533735905, "lat": 37.956803, "lon": -8.8531589, "tags": {"leisure": "playground", "surface": "grass"}}, {"type": "node", "id": 5589363655, "lat": 37.9614185, "lon": -8.867907}, {"type": "node", "id": 5589386446, "lat": 37.9569072, "lon": -8.8636945}, {"type": "node", "id": 5589386447, "lat": 37.9568435, "lon": -8.8637175}, {"type": "node", "id": 5589386450, "lat": 37.9568813, "lon": -8.863692}, {"type": "node", "id": 5589387421, "lat": 37.9567661, "lon": -8.8638596}, {"type": "node", "id": 5589402529, "lat": 37.9588042, "lon": -8.8736341}, {"type": "node", "id": 5589402530, "lat": 37.9589536, "lon": -8.8730725}, {"type": "node", "id": 5589402531, "lat": 37.9592497, "lon": -8.8732067}, {"type": "node", "id": 5589402532, "lat": 37.9592577, "lon": -8.8732247}, {"type": "node", "id": 5589402533, "lat": 37.9592577, "lon": -8.8732665}, {"type": "node", "id": 5589402534, "lat": 37.9592461, "lon": -8.8733003}, {"type": "node", "id": 5589402535, "lat": 37.9592292, "lon": -8.873324}, {"type": "node", "id": 5589402536, "lat": 37.9588487, "lon": -8.8736567}, {"type": "node", "id": 5589402537, "lat": 37.9588344, "lon": -8.87366}, {"type": "node", "id": 5589402538, "lat": 37.9588211, "lon": -8.8736555}, {"type": "node", "id": 5589402539, "lat": 37.9588104, "lon": -8.8736476}, {"type": "node", "id": 5589402540, "lat": 37.9592611, "lon": -8.8732448}, {"type": "node", "id": 5699052215, "lat": 37.9564311, "lon": -8.8549076}, {"type": "node", "id": 5699052216, "lat": 37.9565257, "lon": -8.8551779}, {"type": "node", "id": 5699052217, "lat": 37.9563879, "lon": -8.8552633}, {"type": "node", "id": 5699052218, "lat": 37.9563093, "lon": -8.8549767}, {"type": "node", "id": 5699052219, "lat": 37.9565017, "lon": -8.8552633}, {"type": "node", "id": 5699052220, "lat": 37.9564039, "lon": -8.8553121}, {"type": "node", "id": 5699052421, "lat": 37.9564872, "lon": -8.8556028}, {"type": "node", "id": 5699052422, "lat": 37.956593, "lon": -8.8555194}, {"type": "node", "id": 5699052423, "lat": 37.9565642, "lon": -8.8555967}, {"type": "node", "id": 5699052424, "lat": 37.9567613, "lon": -8.8561557}, {"type": "node", "id": 5699052425, "lat": 37.9566764, "lon": -8.8562106}, {"type": "node", "id": 5699052426, "lat": 37.9565209, "lon": -8.8556251}, {"type": "node", "id": 5699052427, "lat": 37.956827, "lon": -8.8567289}, {"type": "node", "id": 5699052428, "lat": 37.9567693, "lon": -8.8567594}, {"type": "node", "id": 5699052429, "lat": 37.9569504, "lon": -8.8573977}, {"type": "node", "id": 5699052430, "lat": 37.957053, "lon": -8.8573245}, {"type": "node", "id": 5699119795, "lat": 37.9563649, "lon": -8.8577949}, {"type": "node", "id": 5699119796, "lat": 37.9559588, "lon": -8.8581865}, {"type": "node", "id": 5699119797, "lat": 37.9559567, "lon": -8.8582213}, {"type": "node", "id": 5699119798, "lat": 37.9557621, "lon": -8.8584493}, {"type": "node", "id": 5699119799, "lat": 37.9558531, "lon": -8.8585942}, {"type": "node", "id": 5699119800, "lat": 37.9556352, "lon": -8.8588275}, {"type": "node", "id": 5699119801, "lat": 37.9557621, "lon": -8.8590367}, {"type": "node", "id": 5699119802, "lat": 37.9558806, "lon": -8.8586317}, {"type": "node", "id": 5699119803, "lat": 37.9559504, "lon": -8.8584279}, {"type": "node", "id": 5699119804, "lat": 37.9560476, "lon": -8.8581731}, {"type": "node", "id": 5699119805, "lat": 37.9562507, "lon": -8.8582401}, {"type": "node", "id": 5699119806, "lat": 37.9562824, "lon": -8.858157}, {"type": "node", "id": 5699119807, "lat": 37.9564029, "lon": -8.8582187}, {"type": "node", "id": 5699119808, "lat": 37.9564622, "lon": -8.8581301}, {"type": "node", "id": 5699119809, "lat": 37.9563818, "lon": -8.8580202}, {"type": "node", "id": 5699119810, "lat": 37.9563945, "lon": -8.8578324}, {"type": "node", "id": 5699124292, "lat": 37.9555443, "lon": -8.8587041}, {"type": "node", "id": 5699124293, "lat": 37.9550811, "lon": -8.8591869}, {"type": "node", "id": 5699124294, "lat": 37.9557156, "lon": -8.8590475}, {"type": "node", "id": 5699976567, "lat": 37.9558475, "lon": -8.8634293}, {"type": "node", "id": 5700004507, "lat": 37.9615365, "lon": -8.8678382}, {"type": "node", "id": 5711541988, "lat": 37.956819, "lon": -8.8534139, "tags": {"leisure": "playground", "surface": "grass"}}, {"type": "node", "id": 5732308563, "lat": 37.9589197, "lon": -8.8647001}, {"type": "node", "id": 5732308564, "lat": 37.9589754, "lon": -8.8644748}, {"type": "node", "id": 5739998064, "lat": 37.9617986, "lon": -8.8683026}, {"type": "node", "id": 5739998065, "lat": 37.9613525, "lon": -8.8680808}, {"type": "node", "id": 5739998066, "lat": 37.9614841, "lon": -8.8678643}, {"type": "node", "id": 5739998067, "lat": 37.9615644, "lon": -8.8679289}, {"type": "node", "id": 5739998068, "lat": 37.9615952, "lon": -8.8680088}, {"type": "node", "id": 5739998069, "lat": 37.9616217, "lon": -8.8680637}, {"type": "node", "id": 5739998070, "lat": 37.961606, "lon": -8.8680398}, {"type": "node", "id": 5739998071, "lat": 37.9617053, "lon": -8.8681583}, {"type": "node", "id": 5739998072, "lat": 37.9616728, "lon": -8.8681273}, {"type": "node", "id": 5739998074, "lat": 37.9616922, "lon": -8.8681482}, {"type": "node", "id": 5739998075, "lat": 37.9616818, "lon": -8.8681382}, {"type": "node", "id": 5739998076, "lat": 37.9615118, "lon": -8.8678495}, {"type": "node", "id": 5739998077, "lat": 37.961457, "lon": -8.8678782}, {"type": "node", "id": 5739998078, "lat": 37.9613937, "lon": -8.8679545}, {"type": "node", "id": 5740020609, "lat": 37.9600228, "lon": -8.8571778}, {"type": "node", "id": 5740020610, "lat": 37.9601028, "lon": -8.8572095}, {"type": "node", "id": 5740020619, "lat": 37.9603837, "lon": -8.8576488}, {"type": "node", "id": 5740020620, "lat": 37.9604748, "lon": -8.8576203}, {"type": "node", "id": 5740020621, "lat": 37.9605155, "lon": -8.8574844}, {"type": "node", "id": 5740020622, "lat": 37.9601249, "lon": -8.8572193}, {"type": "node", "id": 5740020623, "lat": 37.9600067, "lon": -8.8571705}, {"type": "node", "id": 5740020624, "lat": 37.9596027, "lon": -8.8570025}, {"type": "node", "id": 5740020625, "lat": 37.9593289, "lon": -8.8568687}, {"type": "node", "id": 5740020626, "lat": 37.959319, "lon": -8.8569098}, {"type": "node", "id": 5740020627, "lat": 37.9589123, "lon": -8.8568686}, {"type": "node", "id": 5740020628, "lat": 37.9589037, "lon": -8.8569026}, {"type": "node", "id": 5740020629, "lat": 37.9589466, "lon": -8.8569298}, {"type": "node", "id": 5740020630, "lat": 37.9589712, "lon": -8.8569584}, {"type": "node", "id": 5740020631, "lat": 37.9589819, "lon": -8.8569896}, {"type": "node", "id": 5740020632, "lat": 37.9589884, "lon": -8.8570317}, {"type": "node", "id": 5740020633, "lat": 37.9589916, "lon": -8.8570766}, {"type": "node", "id": 5740020634, "lat": 37.958998, "lon": -8.8571174}, {"type": "node", "id": 5740020635, "lat": 37.9590248, "lon": -8.8571677}, {"type": "node", "id": 5740020636, "lat": 37.959058, "lon": -8.8572152}, {"type": "node", "id": 5740020637, "lat": 37.9591684, "lon": -8.8572791}, {"type": "node", "id": 5740020638, "lat": 37.9592133, "lon": -8.8572989}, {"type": "node", "id": 5740020639, "lat": 37.9596148, "lon": -8.8574907}, {"type": "node", "id": 5740020640, "lat": 37.9598966, "lon": -8.8576225}, {"type": "node", "id": 5740023421, "lat": 37.9558373, "lon": -8.8632087}, {"type": "node", "id": 5740023422, "lat": 37.9559858, "lon": -8.8631702}, {"type": "node", "id": 5740023423, "lat": 37.9557251, "lon": -8.8617132}, {"type": "node", "id": 5740023424, "lat": 37.9555948, "lon": -8.8609482}, {"type": "node", "id": 5740023425, "lat": 37.9555849, "lon": -8.8609187}, {"type": "node", "id": 5740023426, "lat": 37.9553457, "lon": -8.8610741}, {"type": "node", "id": 5740023427, "lat": 37.9550446, "lon": -8.8612971}, {"type": "node", "id": 5740023428, "lat": 37.954904, "lon": -8.8613977}, {"type": "node", "id": 5740023429, "lat": 37.9547531, "lon": -8.8615604}, {"type": "node", "id": 5740023430, "lat": 37.9549964, "lon": -8.8620404}, {"type": "node", "id": 5740023431, "lat": 37.9549928, "lon": -8.8620747}, {"type": "node", "id": 5740023432, "lat": 37.954982, "lon": -8.8621227}, {"type": "node", "id": 5740023433, "lat": 37.9549784, "lon": -8.8621821}, {"type": "node", "id": 5740023434, "lat": 37.9555576, "lon": -8.8636521}, {"type": "node", "id": 5740023435, "lat": 37.9557238, "lon": -8.8635196}, {"type": "node", "id": 5742228985, "lat": 37.9579877, "lon": -8.8696008}, {"type": "node", "id": 5742245656, "lat": 37.9552024, "lon": -8.8642199}, {"type": "node", "id": 5766825914, "lat": 37.9659565, "lon": -8.8567579}, {"type": "node", "id": 5766825915, "lat": 37.9659739, "lon": -8.8567845}, {"type": "node", "id": 5766825916, "lat": 37.965994, "lon": -8.8567633}, {"type": "node", "id": 5766825917, "lat": 37.9659766, "lon": -8.8567368}, {"type": "node", "id": 5766950240, "lat": 37.9623705, "lon": -8.8718783}, {"type": "node", "id": 5766950241, "lat": 37.9624856, "lon": -8.8719786}, {"type": "node", "id": 5766950242, "lat": 37.9625733, "lon": -8.8718168}, {"type": "node", "id": 5766950243, "lat": 37.9624582, "lon": -8.8717164}, {"type": "node", "id": 5766966325, "lat": 37.9586385, "lon": -8.86502}, {"type": "node", "id": 5930308987, "lat": 37.9581284, "lon": -8.8690361}, {"type": "node", "id": 5930308988, "lat": 37.9583993, "lon": -8.8683667}, {"type": "node", "id": 5930311275, "lat": 37.9583876, "lon": -8.8683465}, {"type": "node", "id": 6103981199, "lat": 37.9574049, "lon": -8.863853}, {"type": "node", "id": 6103981200, "lat": 37.9573636, "lon": -8.8640091}, {"type": "node", "id": 6103981201, "lat": 37.9574198, "lon": -8.8639108}, {"type": "node", "id": 6103981202, "lat": 37.9573403, "lon": -8.8640594}, {"type": "node", "id": 6160513278, "lat": 37.9589896, "lon": -8.865995}, {"type": "node", "id": 6160514343, "lat": 37.957421, "lon": -8.8638976}, {"type": "node", "id": 6160514344, "lat": 37.9574193, "lon": -8.8638821}, {"type": "node", "id": 6160514345, "lat": 37.9574153, "lon": -8.8638688}, {"type": "node", "id": 6160514346, "lat": 37.95733, "lon": -8.8640957}, {"type": "node", "id": 6165057986, "lat": 37.95583, "lon": -8.8728498}, {"type": "node", "id": 6165057987, "lat": 37.9558367, "lon": -8.8728396}, {"type": "node", "id": 6165057988, "lat": 37.9558434, "lon": -8.872824}, {"type": "node", "id": 6165057989, "lat": 37.9558262, "lon": -8.8728516}, {"type": "node", "id": 6332170957, "lat": 37.9568523, "lon": -8.8637057}, {"type": "node", "id": 6347712881, "lat": 37.9610754, "lon": -8.8714428}, {"type": "node", "id": 6347712882, "lat": 37.9605357, "lon": -8.8706984}, {"type": "node", "id": 6347712883, "lat": 37.9604095, "lon": -8.8711282}, {"type": "node", "id": 6347712884, "lat": 37.9612016, "lon": -8.8710131}, {"type": "node", "id": 6347712885, "lat": 37.9609335, "lon": -8.8718204}, {"type": "node", "id": 6347712886, "lat": 37.9610434, "lon": -8.8714556}, {"type": "node", "id": 6347712887, "lat": 37.9607897, "lon": -8.8717453}, {"type": "node", "id": 6347712888, "lat": 37.960898, "lon": -8.8713837}, {"type": "node", "id": 6347712889, "lat": 37.9608559, "lon": -8.8718306}, {"type": "node", "id": 6347712890, "lat": 37.960898, "lon": -8.8719072}, {"type": "node", "id": 6347712891, "lat": 37.9608949, "lon": -8.8718783}, {"type": "node", "id": 6347712892, "lat": 37.9608806, "lon": -8.8718493}, {"type": "node", "id": 6347712893, "lat": 37.9607884, "lon": -8.8718305}, {"type": "node", "id": 6347712894, "lat": 37.9608224, "lon": -8.8718214}, {"type": "node", "id": 6347712895, "lat": 37.9608403, "lon": -8.8718243}, {"type": "node", "id": 6347712896, "lat": 37.9607674, "lon": -8.8718438}, {"type": "node", "id": 6347712897, "lat": 37.9608034, "lon": -8.8718228}, {"type": "node", "id": 6347712898, "lat": 37.9608885, "lon": -8.8718611}, {"type": "node", "id": 6347712899, "lat": 37.9608692, "lon": -8.8718399}, {"type": "node", "id": 6347712900, "lat": 37.9607771, "lon": -8.872399}, {"type": "node", "id": 6347712901, "lat": 37.9607585, "lon": -8.872462}, {"type": "node", "id": 6347712902, "lat": 37.9605854, "lon": -8.872384}, {"type": "node", "id": 6347712903, "lat": 37.9606038, "lon": -8.872323}, {"type": "node", "id": 6347712904, "lat": 37.9606993, "lon": -8.8724671}, {"type": "node", "id": 6347712905, "lat": 37.9607276, "lon": -8.8724516}, {"type": "node", "id": 6347712906, "lat": 37.9606614, "lon": -8.8724644}, {"type": "node", "id": 6347712907, "lat": 37.9606149, "lon": -8.8723974}, {"type": "node", "id": 6347712908, "lat": 37.9606392, "lon": -8.872447}, {"type": "node", "id": 6347712909, "lat": 37.9606228, "lon": -8.8724302}, {"type": "node", "id": 6347712910, "lat": 37.9606156, "lon": -8.872413}, {"type": "node", "id": 6347712911, "lat": 37.9606787, "lon": -8.872469}, {"type": "node", "id": 6347712912, "lat": 37.9596734, "lon": -8.8707155}, {"type": "node", "id": 6347712913, "lat": 37.9597088, "lon": -8.8706044}, {"type": "node", "id": 6550198469, "lat": 37.9549835, "lon": -8.8619807}, {"type": "node", "id": 6550198470, "lat": 37.955754, "lon": -8.8632334}, {"type": "node", "id": 6550198471, "lat": 37.9555095, "lon": -8.8619141}, {"type": "node", "id": 6550198472, "lat": 37.9554922, "lon": -8.8620803}, {"type": "node", "id": 6550198473, "lat": 37.9554462, "lon": -8.8620422}, {"type": "node", "id": 6550198474, "lat": 37.9553966, "lon": -8.862025}, {"type": "node", "id": 6550198475, "lat": 37.9553429, "lon": -8.8620058}, {"type": "node", "id": 6550198476, "lat": 37.9552724, "lon": -8.8619973}, {"type": "node", "id": 6550198477, "lat": 37.9552204, "lon": -8.8620058}, {"type": "node", "id": 6550198478, "lat": 37.95517, "lon": -8.8620314}, {"type": "node", "id": 6550198479, "lat": 37.9551163, "lon": -8.8620803}, {"type": "node", "id": 6550198480, "lat": 37.9550844, "lon": -8.8621272}, {"type": "node", "id": 6550198481, "lat": 37.9550508, "lon": -8.8621889}, {"type": "node", "id": 6550198482, "lat": 37.9550307, "lon": -8.8622613}, {"type": "node", "id": 6550198483, "lat": 37.9550307, "lon": -8.8623358}, {"type": "node", "id": 6550198484, "lat": 37.9551926, "lon": -8.8632869}, {"type": "node", "id": 6550203785, "lat": 37.9552379, "lon": -8.8633784}, {"type": "node", "id": 6550203786, "lat": 37.9553084, "lon": -8.8634551}, {"type": "node", "id": 6550203787, "lat": 37.9553897, "lon": -8.8634813}, {"type": "node", "id": 6550203788, "lat": 37.9554808, "lon": -8.8634805}, {"type": "node", "id": 6550203789, "lat": 37.9555618, "lon": -8.8634528}, {"type": "node", "id": 6550203790, "lat": 37.9556909, "lon": -8.8633116}, {"type": "node", "id": 6550203794, "lat": 37.9556632, "lon": -8.8628246}, {"type": "node", "id": 6550203796, "lat": 37.9556117, "lon": -8.8625196}, {"type": "node", "id": 6550203797, "lat": 37.9555799, "lon": -8.8623308}, {"type": "node", "id": 6550203799, "lat": 37.9552123, "lon": -8.8633358}, {"type": "node", "id": 6550203800, "lat": 37.9552698, "lon": -8.8634189}, {"type": "node", "id": 6550203801, "lat": 37.9553418, "lon": -8.8634748}, {"type": "node", "id": 6550203802, "lat": 37.955436, "lon": -8.8634858}, {"type": "node", "id": 6550203803, "lat": 37.9555208, "lon": -8.8634729}, {"type": "node", "id": 6550203804, "lat": 37.9553705, "lon": -8.8634797}, {"type": "node", "id": 6550203805, "lat": 37.9554102, "lon": -8.8634842}, {"type": "node", "id": 6550203806, "lat": 37.9554584, "lon": -8.8634831}, {"type": "node", "id": 6550203807, "lat": 37.9555018, "lon": -8.863478}, {"type": "node", "id": 6550203808, "lat": 37.9555415, "lon": -8.8634642}, {"type": "node", "id": 6550203809, "lat": 37.9555829, "lon": -8.8634361}, {"type": "node", "id": 6550203810, "lat": 37.9556047, "lon": -8.8634253}, {"type": "node", "id": 7159602960, "lat": 37.955339, "lon": -8.8668645}, {"type": "node", "id": 9921700000, "lat": 37.9571429, "lon": -8.8607838}, {"type": "node", "id": 11165126080, "lat": 37.9579022, "lon": -8.8603241}, {"type": "node", "id": 11165126081, "lat": 37.95785, "lon": -8.8605139}, {"type": "node", "id": 11165126082, "lat": 37.9580272, "lon": -8.8605923}, {"type": "node", "id": 11165126083, "lat": 37.9580794, "lon": -8.8604026}, {"type": "node", "id": 11165862363, "lat": 37.9569456, "lon": -8.8583629}, {"type": "node", "id": 11165862364, "lat": 37.9572194, "lon": -8.8584991}, {"type": "node", "id": 11165862365, "lat": 37.95728, "lon": -8.8583031}, {"type": "node", "id": 11165862366, "lat": 37.9570061, "lon": -8.8581669}, {"type": "node", "id": 11170604573, "lat": 37.9568725, "lon": -8.8530467}, {"type": "node", "id": 11170604574, "lat": 37.9566604, "lon": -8.8531834}, {"type": "node", "id": 11170604575, "lat": 37.9568247, "lon": -8.8535936}, {"type": "node", "id": 11170604576, "lat": 37.9570368, "lon": -8.853457}, {"type": "node", "id": 11172009857, "lat": 37.9564086, "lon": -8.8598811}, {"type": "node", "id": 11172009858, "lat": 37.9565536, "lon": -8.8594066}, {"type": "node", "id": 11172009859, "lat": 37.9568114, "lon": -8.8595332}, {"type": "node", "id": 11193274804, "lat": 37.9575855, "lon": -8.8787441}, {"type": "node", "id": 11193274805, "lat": 37.9575749, "lon": -8.8787701}, {"type": "node", "id": 11193274806, "lat": 37.9575719, "lon": -8.8787991}, {"type": "node", "id": 11193274807, "lat": 37.9575769, "lon": -8.8788276}, {"type": "node", "id": 11193274808, "lat": 37.9575893, "lon": -8.8788522}, {"type": "node", "id": 11193274809, "lat": 37.9576076, "lon": -8.87887}, {"type": "node", "id": 11193274810, "lat": 37.9576296, "lon": -8.8788787}, {"type": "node", "id": 11193274811, "lat": 37.9576526, "lon": -8.8788774}, {"type": "node", "id": 11193274812, "lat": 37.9576909, "lon": -8.8788464}, {"type": "node", "id": 11193274813, "lat": 37.9577015, "lon": -8.8788205}, {"type": "node", "id": 11193274814, "lat": 37.9577045, "lon": -8.8787915}, {"type": "node", "id": 11193274815, "lat": 37.9576995, "lon": -8.878763}, {"type": "node", "id": 11193274816, "lat": 37.9576871, "lon": -8.8787384}, {"type": "node", "id": 11193274817, "lat": 37.9576688, "lon": -8.8787206}, {"type": "node", "id": 11193274818, "lat": 37.9576468, "lon": -8.8787118}, {"type": "node", "id": 11193274819, "lat": 37.9576238, "lon": -8.8787132}, {"type": "node", "id": 11193274820, "lat": 37.9576739, "lon": -8.8788662}, {"type": "node", "id": 11193274821, "lat": 37.9578402, "lon": -8.8788706}, {"type": "node", "id": 11193274822, "lat": 37.9577398, "lon": -8.8786694}, {"type": "node", "id": 11193274823, "lat": 37.9578362, "lon": -8.878592}, {"type": "node", "id": 11193274824, "lat": 37.9579367, "lon": -8.8787931}, {"type": "node", "id": 11978734839, "lat": 37.9568444, "lon": -8.8810136}, {"type": "node", "id": 11978734840, "lat": 37.9567989, "lon": -8.8811102}, {"type": "node", "id": 11978734841, "lat": 37.956755, "lon": -8.8810612}, {"type": "node", "id": 11978787970, "lat": 37.9557734, "lon": -8.864135}, {"type": "node", "id": 11978787971, "lat": 37.955724, "lon": -8.8641843}, {"type": "node", "id": 11978787972, "lat": 37.9557135, "lon": -8.8641768}, {"type": "node", "id": 11978787973, "lat": 37.9557728, "lon": -8.8641508}, {"type": "node", "id": 11978787974, "lat": 37.955768, "lon": -8.8641654}, {"type": "node", "id": 11978787975, "lat": 37.9557596, "lon": -8.8641772}, {"type": "node", "id": 11978787976, "lat": 37.9557486, "lon": -8.8641847}, {"type": "node", "id": 11978787977, "lat": 37.9557362, "lon": -8.8641872}, {"type": "node", "id": 11978787978, "lat": 37.9557009, "lon": -8.8641514}, {"type": "node", "id": 11978787979, "lat": 37.9557, "lon": -8.8641362}, {"type": "node", "id": 11978787980, "lat": 37.955703, "lon": -8.8641215}, {"type": "node", "id": 11978787981, "lat": 37.9557096, "lon": -8.8641088}, {"type": "node", "id": 11978787982, "lat": 37.955719, "lon": -8.8640994}, {"type": "node", "id": 11978787983, "lat": 37.9557303, "lon": -8.8640943}, {"type": "node", "id": 11978787984, "lat": 37.9557423, "lon": -8.8640941}, {"type": "node", "id": 11978787985, "lat": 37.9557537, "lon": -8.8640988}, {"type": "node", "id": 11978787986, "lat": 37.9557633, "lon": -8.8641079}, {"type": "node", "id": 11978787987, "lat": 37.9557701, "lon": -8.8641203}, {"type": "node", "id": 12009901768, "lat": 37.955839, "lon": -8.8586213}, {"type": "node", "id": 12009901815, "lat": 37.9556518, "lon": -8.8588097}, {"type": "node", "id": 12152666236, "lat": 37.9552717, "lon": -8.8525888}, {"type": "node", "id": 12241193435, "lat": 37.9572079, "lon": -8.8591516}, {"type": "node", "id": 12241193439, "lat": 37.9572558, "lon": -8.8589337}, {"type": "node", "id": 12241193450, "lat": 37.9572534, "lon": -8.8590033}, {"type": "node", "id": 12241193478, "lat": 37.9571381, "lon": -8.8591171}, {"type": "node", "id": 12241193497, "lat": 37.9572974, "lon": -8.8588104}, {"type": "node", "id": 12241197322, "lat": 37.9573403, "lon": -8.8589796}, {"type": "node", "id": 12241197330, "lat": 37.9571835, "lon": -8.8589688}, {"type": "node", "id": 12241197340, "lat": 37.9573819, "lon": -8.8588562}, {"type": "node", "id": 12246005295, "lat": 37.9594578, "lon": -8.8805896, "tags": {"leisure": "pitch"}}, {"type": "node", "id": 12836813664, "lat": 37.9554681, "lon": -8.8619236}, {"type": "node", "id": 12836813665, "lat": 37.9554655, "lon": -8.8621593}, {"type": "node", "id": 12836813666, "lat": 37.9554271, "lon": -8.8621167}, {"type": "node", "id": 12836813667, "lat": 37.9553818, "lon": -8.8620848}, {"type": "node", "id": 12836813668, "lat": 37.9553281, "lon": -8.8620656}, {"type": "node", "id": 12836813669, "lat": 37.9552804, "lon": -8.8620603}, {"type": "node", "id": 12836813670, "lat": 37.9552046, "lon": -8.8620828}, {"type": "node", "id": 12836813671, "lat": 37.9551591, "lon": -8.8621331}, {"type": "node", "id": 12836813672, "lat": 37.9551199, "lon": -8.8621832}, {"type": "node", "id": 12836813673, "lat": 37.955089, "lon": -8.8622326}, {"type": "node", "id": 12836813674, "lat": 37.9550816, "lon": -8.8623115}, {"type": "node", "id": 12836813675, "lat": 37.9550811, "lon": -8.8623566}, {"type": "node", "id": 12836813676, "lat": 37.9552329, "lon": -8.86323}, {"type": "node", "id": 12836813677, "lat": 37.9555062, "lon": -8.8622128}, {"type": "node", "id": 12836813678, "lat": 37.9556669, "lon": -8.8631225}, {"type": "node", "id": 12836813679, "lat": 37.9555136, "lon": -8.8622498}, {"type": "node", "id": 12836813680, "lat": 37.9556644, "lon": -8.8633569}, {"type": "node", "id": 12837135644, "lat": 37.9552401, "lon": -8.8620669}, {"type": "node", "id": 12837135645, "lat": 37.9552552, "lon": -8.8632908}, {"type": "node", "id": 12837135646, "lat": 37.95529, "lon": -8.8633404}, {"type": "node", "id": 12837135647, "lat": 37.9553266, "lon": -8.8633714}, {"type": "node", "id": 12837135648, "lat": 37.9553651, "lon": -8.8633946}, {"type": "node", "id": 12837135649, "lat": 37.9554072, "lon": -8.8634093}, {"type": "node", "id": 12837135650, "lat": 37.955453, "lon": -8.8634155}, {"type": "node", "id": 12837135651, "lat": 37.9554994, "lon": -8.8634101}, {"type": "node", "id": 12837135652, "lat": 37.9555397, "lon": -8.8633868}, {"type": "node", "id": 12837135653, "lat": 37.9555775, "lon": -8.8633582}, {"type": "node", "id": 12837135654, "lat": 37.9556062, "lon": -8.8633311}, {"type": "node", "id": 12837135655, "lat": 37.9556313, "lon": -8.8632908}, {"type": "node", "id": 12837135656, "lat": 37.9556502, "lon": -8.8632521}, {"type": "node", "id": 12837135657, "lat": 37.955663, "lon": -8.8631994}, {"type": "node", "id": 12837135658, "lat": 37.9556679, "lon": -8.8631569}, {"type": "node", "id": 12837135659, "lat": 37.9556344, "lon": -8.8634038}, {"type": "node", "id": 12837216397, "lat": 37.9555045, "lon": -8.8636397}, {"type": "node", "id": 12837216398, "lat": 37.9554509, "lon": -8.8634961}, {"type": "node", "id": 12837216399, "lat": 37.955496, "lon": -8.8634907}, {"type": "node", "id": 12837216400, "lat": 37.9555279, "lon": -8.8634839}, {"type": "node", "id": 12837235901, "lat": 37.9555673, "lon": -8.8634678}, {"type": "node", "id": 12837235902, "lat": 37.9556119, "lon": -8.8634435}, {"type": "node", "id": 12837235903, "lat": 37.9556523, "lon": -8.8634024}, {"type": "node", "id": 12837235904, "lat": 37.9556757, "lon": -8.8633687}, {"type": "node", "id": 12837235905, "lat": 37.9556948, "lon": -8.8633289}, {"type": "node", "id": 12837235906, "lat": 37.9557108, "lon": -8.8633107}, {"type": "node", "id": 12837235907, "lat": 37.9557299, "lon": -8.8632864}, {"type": "node", "id": 12837235908, "lat": 37.955799, "lon": -8.8634185}, {"type": "node", "id": 12837514958, "lat": 37.9555814, "lon": -8.8629811}, {"type": "node", "id": 12837514959, "lat": 37.9554711, "lon": -8.8624198}, {"type": "node", "id": 12837514960, "lat": 37.9554294, "lon": -8.8623365}, {"type": "node", "id": 12837514961, "lat": 37.9553968, "lon": -8.8623088}, {"type": "node", "id": 12837514962, "lat": 37.9552201, "lon": -8.8623622}, {"type": "node", "id": 12837514963, "lat": 37.9552009, "lon": -8.8624056}, {"type": "node", "id": 12837514964, "lat": 37.9551917, "lon": -8.862454}, {"type": "node", "id": 12837514965, "lat": 37.9551933, "lon": -8.8625038}, {"type": "node", "id": 12837514966, "lat": 37.9553595, "lon": -8.8622933}, {"type": "node", "id": 12837514967, "lat": 37.9553203, "lon": -8.8622912}, {"type": "node", "id": 12837514968, "lat": 37.9552821, "lon": -8.8623027}, {"type": "node", "id": 12837514969, "lat": 37.9552478, "lon": -8.862327}, {"type": "node", "id": 12837514970, "lat": 37.955528, "lon": -8.8624225}, {"type": "node", "id": 12837514971, "lat": 37.9555037, "lon": -8.862348}, {"type": "node", "id": 12837514972, "lat": 37.9554617, "lon": -8.8622875}, {"type": "node", "id": 12837514973, "lat": 37.9554064, "lon": -8.8622476}, {"type": "node", "id": 12837514974, "lat": 37.955344, "lon": -8.8622326}, {"type": "node", "id": 12837514975, "lat": 37.955281, "lon": -8.8622441}, {"type": "node", "id": 12837514976, "lat": 37.9551469, "lon": -8.8624924}, {"type": "node", "id": 12837514977, "lat": 37.9552245, "lon": -8.8622809}, {"type": "node", "id": 12837514978, "lat": 37.9551804, "lon": -8.862339}, {"type": "node", "id": 12837514979, "lat": 37.9551536, "lon": -8.8624121}, {"type": "node", "id": 12837514980, "lat": 37.9555782, "lon": -8.8631798}, {"type": "node", "id": 12837514981, "lat": 37.9556141, "lon": -8.8631133}, {"type": "node", "id": 12837514982, "lat": 37.9556311, "lon": -8.8630356}, {"type": "node", "id": 12837514983, "lat": 37.9556284, "lon": -8.8629907}, {"type": "node", "id": 12837514984, "lat": 37.9552604, "lon": -8.8631035}, {"type": "node", "id": 12837514985, "lat": 37.955294, "lon": -8.863172}, {"type": "node", "id": 12837514986, "lat": 37.9553433, "lon": -8.8632229}, {"type": "node", "id": 12837514987, "lat": 37.955403, "lon": -8.8632507}, {"type": "node", "id": 12837514988, "lat": 37.9554666, "lon": -8.8632525}, {"type": "node", "id": 12837514989, "lat": 37.9555272, "lon": -8.863228}, {"type": "node", "id": 12837514990, "lat": 37.9553068, "lon": -8.8631035}, {"type": "node", "id": 12837514991, "lat": 37.9553362, "lon": -8.8631469}, {"type": "node", "id": 12837514992, "lat": 37.9553755, "lon": -8.8631811}, {"type": "node", "id": 12837514993, "lat": 37.9554215, "lon": -8.863197}, {"type": "node", "id": 12837514994, "lat": 37.955469, "lon": -8.8631927}, {"type": "node", "id": 12837514995, "lat": 37.9555128, "lon": -8.8631688}, {"type": "node", "id": 12837514996, "lat": 37.9555479, "lon": -8.8631279}, {"type": "node", "id": 12837514997, "lat": 37.9555704, "lon": -8.8630746}, {"type": "node", "id": 12837514998, "lat": 37.9555827, "lon": -8.8630296}, {"type": "node", "id": 12837514999, "lat": 37.9552915, "lon": -8.8630582}, {"type": "node", "id": 12837515000, "lat": 37.9554548, "lon": -8.8623745}, {"type": "way", "id": 51353485, "nodes": [655309038, 655309039, 655309041, 655309043, 655309038], "tags": {"leisure": "pitch", "sport": "handball"}}, {"type": "way", "id": 51353487, "nodes": [655309047, 655309048, 655309049, 655309051, 655309047], "tags": {"leisure": "pitch", "lit": "yes", "name": "Vasco da Gama Atl\u00e9tico Clube", "sport": "futebol", "surface": "grass"}}, {"type": "way", "id": 103079645, "nodes": [1190104184, 1190104209, 1190104264, 5742228985, 1190104161, 1190104184], "tags": {"leisure": "sports_centre"}}, {"type": "way", "id": 103079648, "nodes": [1190104148, 1190104196, 6347712890, 6347712891, 6347712898, 6347712892, 6347712899, 6347712889, 6347712895, 6347712894, 6347712897, 6347712893, 6347712896, 1190104223, 1190104140, 6347712903, 6347712902, 6347712907, 6347712910, 6347712909, 6347712908, 6347712906, 6347712911, 6347712904, 6347712905, 6347712901, 6347712900, 1190104148], "tags": {"leisure": "sports_centre"}}, {"type": "way", "id": 162848230, "nodes": [1746641407, 1746641199, 1746641318, 1746641180, 1746641407], "tags": {"leisure": "pitch", "sport": "soccer", "surface": "grass_paver"}}, {"type": "way", "id": 162848231, "nodes": [1746641300, 5260518316, 6160513278, 5491415764, 1746641324, 1745730880, 5260518315, 1746641248, 1746641285, 1746641275, 5302702877, 5263953744, 5302702876, 5302704691, 1746641362, 1746641413, 5260518314, 5260518313, 5732308564, 5732308563, 1746641213, 1746641098, 1746641216, 5256816151, 5260518312, 5260518311, 1746641406, 5302702875, 5766966325, 5256816146, 5260518310, 5260518318, 1746641320, 1746641338, 5262641058, 5260520527, 1746641300], "tags": {"leisure": "park", "name": "Jardim da Alameda da Paz", "surface": "grass"}}, {"type": "way", "id": 241498683, "nodes": [2491171229, 2491171231, 2491171234, 2491171236, 2491171239, 2491171242, 2491171229], "tags": {"leisure": "garden", "name": "Jardim da Boavista"}}, {"type": "way", "id": 257184808, "nodes": [2627816834, 2627816836, 2627816823, 2648832737, 2627816820, 2627816834], "tags": {"leisure": "park", "surface": "grass"}}, {"type": "way", "id": 263289234, "nodes": [2689090907, 2689090912, 2689090915, 2689090918, 2689090922, 2689090926, 2689090929, 2689090932, 2689090935, 2689090938, 2689090942, 2689090944, 2689090946, 2689090949, 2689090951, 2689090953, 2689090955, 2689090907], "tags": {"leisure": "garden"}}, {"type": "way", "id": 263289235, "nodes": [2689090957, 2689090959, 2689090961, 2689090963, 2689090964, 2689090967, 2689090969, 2689090971, 2689090973, 2689090975, 2689090980, 2689090977, 2689090957], "tags": {"leisure": "garden"}}, {"type": "way", "id": 263293336, "nodes": [2689139547, 2689139548, 2689139549, 2689139550, 2689139547], "tags": {"leisure": "playground", "surface": "tartan"}}, {"type": "way", "id": 264027817, "nodes": [2697017826, 2697017827, 2697017828, 2697017829, 2697017826], "tags": {"leisure": "playground"}}, {"type": "way", "id": 264029242, "nodes": [2697037949, 2697037962, 2697037968, 2697037950, 2697037951, 2697037957, 2697037952, 2697037960, 2697037953, 2697037954, 2697037955, 2697037959, 2697037949], "tags": {"addr:city": "Sines", "addr:country": "PT", "leisure": "sports_centre"}}, {"type": "way", "id": 264029243, "nodes": [2697037962, 2697037964, 2697037966, 2697037968, 2697037962], "tags": {"addr:city": "Sines", "addr:country": "PT", "leisure": "playground"}}, {"type": "way", "id": 264029244, "nodes": [2697037970, 2697037971, 2697037973, 2697037975, 2697037979, 2697037970], "tags": {"leisure": "pitch", "sport": "soccer", "surface": "grass_paver"}}, {"type": "way", "id": 264029955, "nodes": [2697067682, 2697067683, 2697067689, 2697067685, 2697067682], "tags": {"leisure": "pitch", "sport": "tennis", "surface": "paved"}}, {"type": "way", "id": 264029956, "nodes": [2697067685, 2697067686, 2697067688, 2697067689, 2697067685], "tags": {"leisure": "pitch", "sport": "tennis", "surface": "paved"}}, {"type": "way", "id": 264029957, "nodes": [2697067691, 2697067692, 2697067693, 2697067695, 2697067691], "tags": {"leisure": "pitch", "sport": "volleyball", "surface": "paved"}}, {"type": "way", "id": 264029958, "nodes": [2697067696, 2697067697, 2697067699, 2697067700, 2697067696], "tags": {"leisure": "pitch"}}, {"type": "way", "id": 264543417, "nodes": [2702090551, 2702090552, 2702090553, 2702090554, 2702090555, 2702090556, 2702090557, 2702090558, 2702090559, 2702090560, 2702090561, 2702090562, 2702090563, 2702090564, 2702090565, 2702090566, 2702090567, 2702090568, 2702090569, 2702090551], "tags": {"leisure": "park"}}, {"type": "way", "id": 265126198, "nodes": [2707858717, 5365093291, 2707858718, 2707858719, 2707858720, 2707858717], "tags": {"leisure": "swimming_pool", "surface": "grass"}}, {"type": "way", "id": 265139309, "nodes": [2707967440, 2707967441, 2707967442, 5262683054, 6160514346, 6103981202, 6103981200, 6103981201, 6160514343, 6160514344, 6160514345, 6103981199, 5041868926, 5041868685, 881633443, 5589386446, 5589386450, 2707967447, 6332170957, 5589386447, 5041868653, 5589387421, 2707967448, 5262683060, 2707967449, 2707967450, 5262683059, 5262683058, 2707967451, 2707967440], "tags": {"bench": "yes", "leisure": "garden", "name": "Jardim da Rep\u00fablica"}}, {"type": "way", "id": 291943407, "nodes": [2954468906, 2954468913, 5264764588, 2954468921, 5302709108, 2954468904, 2954468910, 2954468905, 2954468919, 2954468917, 2954468915, 2954468911, 12152666236, 2954468912, 2954468914, 2954468918, 2954468906], "tags": {"building": "yes", "leisure": "sports_centre", "name": "Piscina Municipal de Sines", "sport": "swimming"}}, {"type": "way", "id": 292076528, "nodes": [2955899402, 2955899453, 2955899382, 2955899374, 2955899403, 2955899516, 2955899471, 2955899482, 2955899518, 2955899450, 2955899485, 2955899481, 2955899428, 2955899484, 2955899493, 2955899444, 2955899429, 2955899507, 2955899496, 2955899442, 2955899409, 2955899462, 2955899426, 2955899388, 2955899406, 2955899492, 2955899370, 2955899480, 2955899447, 2955899476, 2955899359, 2955899367, 2955899436, 2955899396, 2955899413, 2955899411, 2955899491, 2955899431, 2955899464, 2955899495, 2955899437, 2955899424, 2955899341, 2955899412, 2955899351, 2955899490, 2955899469, 2955899416, 2955899472, 2955899343, 2955899333, 2955899423, 2955899425, 2955899398, 2955899478, 2955899369, 2955899364, 2955899349, 2955899345, 2955899408, 2955899457, 2955899441, 2955899506, 2955899397, 2955899357, 2955899451, 2955899513, 2955899415, 2955899402]}, {"type": "way", "id": 292076529, "nodes": [2955899446, 2955899479, 2955899394, 2955899474, 2955899373, 2955899360, 2955899365, 2955899410, 2955899352, 2955899390, 2955899376, 2955899404, 2955899348, 2955899387, 2955899422, 2955899381, 2955899363, 2955899448, 2955899501, 2955899400, 2955899338, 2955899446]}, {"type": "way", "id": 292076530, "nodes": [2955899421, 2955899459, 2955899443, 2955899334, 2955899335, 2955899383, 2955899389, 2955899511, 2955899454, 2955899466, 2955899510, 2955899514, 2955899356, 2955899353, 2955899377, 2955899419, 2955899440, 2955899434, 2955899392, 2955899483, 2955899380, 2955899361, 2955899362, 2955899421]}, {"type": "way", "id": 292076533, "nodes": [2955899368, 2955899517, 2955899391, 2955899467, 2955899435, 2955899486, 2955899358, 2955899339, 2955899340, 2955899395, 2955899468, 2955899461, 2955899418, 2955899497, 2955899508, 2955899355, 2955899463, 2955899401, 2955899336, 2955899488, 2955899489, 2955899378, 2955899452, 2955899344, 2955899445, 2955899458, 2955899342, 2955899477, 2955899449, 2955899487, 2955899405, 2955899337, 2955899503, 2955899504, 2955899393, 2955899384, 2955899512, 2955899368]}, {"type": "way", "id": 468773953, "nodes": [4632423370, 5303842117, 5303842118, 5930308987, 2710131716, 5264746708, 5264746695, 5264746696, 5257551347, 5930308988, 5257551348, 5930311275, 5367245023, 4632423371, 4632423372, 5452305740, 4632423373, 5257551346, 5319303251, 4640750104, 4640750103, 2586594704, 4632423374, 1745543493, 5301603124, 4640750110, 4640750109, 4640750108, 5431893860, 4640750107, 4632423375, 4640750105, 4640750106, 5332241346, 1745543666, 5319303241, 4632472985, 4632423370], "tags": {"leisure": "park", "name": "Jardim das Descobertas", "surface": "grass"}}, {"type": "way", "id": 543794356, "nodes": [5256790932, 5256790938, 5256790933, 5256790934, 5305605971, 5256790936, 5256790939, 6165057988, 6165057987, 6165057986, 6165057989, 5256790940, 5256790932], "tags": {"leisure": "park"}}, {"type": "way", "id": 543797743, "nodes": [5256816339, 5742245656, 5301612236, 5444096908, 5301612234, 5444096910, 5444096911, 5444096909, 5444096912, 5301612233, 5301612232, 5301612231, 5740023434, 5740023435, 5699976567, 5256816344, 5333385247, 5256816345, 5333385243, 5256816346, 5256816347, 5333385239, 5256816339], "tags": {"leisure": "park", "name": "IOS", "surface": "grass", "surface_1": "sand"}}, {"type": "way", "id": 544412928, "nodes": [5262690970, 5262690971, 5262690981, 5262690972, 5262690980, 5284945737, 5262690970], "tags": {"leisure": "pitch", "lit": "yes", "name": "Campo Sint\u00e9tico", "sport": "futebol", "surface": "artificial_turf"}}, {"type": "way", "id": 544412929, "nodes": [5262690974, 1190104218, 5262690975, 5262690976, 5262690977, 1190104209, 1190104184, 5262690980, 5262690972, 5262690981, 5262690974], "tags": {"leisure": "sports_centre"}}, {"type": "way", "id": 544412930, "nodes": [5262690980, 1190104184, 1190104161, 5262690983, 5284945735, 5284945736, 5262690980], "tags": {"leisure": "sports_centre", "name": "Pavilh\u00e3o Municipal dos Desportos", "sport": "hockey"}}, {"type": "way", "id": 544654943, "nodes": [5264755441, 5264755442, 5264755443, 5264755444, 5264755441], "tags": {"access": "yes", "leisure": "playground", "surface": "wood"}}, {"type": "way", "id": 546932353, "nodes": [5284944278, 1190104185, 1190104210, 1190104266, 5262690970, 5262690971, 5262690972, 5284945736, 5284945735, 5284944279, 5284944280, 5284944281, 5284944282, 5284944283, 5284944284, 5284944285, 5284944286, 5284944287, 5284944288, 5284944289, 6347712913, 6347712912, 5284944278], "tags": {"leisure": "stadium", "name": "Est\u00e1dio Municipal de Sines"}}, {"type": "way", "id": 548796489, "nodes": [11172009857, 5301606926, 5301606922, 11172009859, 11172009858, 11172009857], "tags": {"leisure": "garden", "surface": "grass"}}, {"type": "way", "id": 549664327, "nodes": [5309598818, 5309598819, 5309598820, 5309600521, 5309598818], "tags": {"leisure": "park"}}, {"type": "way", "id": 549664328, "nodes": [5309600522, 5309600523, 5309600524, 5309600525, 5309600522], "tags": {"leisure": "playground"}}, {"type": "way", "id": 554350533, "nodes": [5349965148, 5349965149, 5349965150, 9921700000, 5349965148], "tags": {"leisure": "garden"}}, {"type": "way", "id": 584788453, "nodes": [5589402529, 5589402530, 5589402531, 5589402532, 5589402540, 5589402533, 5589402534, 5589402535, 5589402536, 5589402537, 5589402538, 5589402539, 5589402529], "tags": {"leisure": "park"}}, {"type": "way", "id": 598831499, "nodes": [5699052215, 5699052216, 5699052217, 5699052218, 5699052215], "tags": {"leisure": "garden", "surface": "grass"}}, {"type": "way", "id": 598831500, "nodes": [5699052219, 5699052220, 5699052421, 5699052422, 5699052219], "tags": {"leisure": "garden", "surface": "grass"}}, {"type": "way", "id": 598831501, "nodes": [5699052423, 5699052424, 5699052425, 5699052426, 5699052423], "tags": {"leisure": "garden", "surface": "grass"}}, {"type": "way", "id": 598831502, "nodes": [5699052427, 5699052428, 5699052429, 5699052430, 5699052427], "tags": {"leisure": "garden", "surface": "grass"}}, {"type": "way", "id": 598843590, "nodes": [5699119795, 5699119796, 5699119797, 5699119798, 5699119799, 12009901768, 12009901815, 5699119800, 5699119801, 5699119802, 5699119803, 5699119804, 5699119805, 5699119806, 5699119807, 5699119808, 5699119809, 5699119810, 5699119795], "tags": {"leisure": "garden", "surface": "grass"}}, {"type": "way", "id": 598844321, "nodes": [5699124292, 5699124293, 5699124294, 5699124292], "tags": {"leisure": "garden", "surface": "grass"}}, {"type": "way", "id": 598983150, "nodes": [5589363655, 5739998077, 5739998066, 5739998076, 5700004507, 5739998067, 5739998068, 5739998070, 5739998069, 5739998072, 5739998075, 5739998074, 5739998071, 5303837395, 5739998064, 5739998065, 5739998078, 5589363655], "tags": {"leisure": "park", "surface": "grass"}}, {"type": "way", "id": 605099428, "nodes": [5491415790, 5740020619, 5740020620, 5740020621, 5491415795, 5491415792, 5491415799, 5491415796, 5740020622, 5740020610, 5740020609, 5740020623, 5491415803, 5491415800, 5491415925, 5491415924, 5491415923, 5740020624, 5740020625, 5740020626, 5491415818, 5491415921, 5491415820, 5491415817, 5491415816, 5740020627, 5740020628, 5740020629, 5740020630, 5740020631, 5740020632, 5740020633, 5740020634, 5740020635, 5740020636, 5740020637, 5740020638, 5491415932, 5491415931, 5491415930, 5491415926, 5491415927, 5491415928, 5740020639, 5740020640, 5491415784, 5491415785, 5491415786, 5491415789, 5491415790], "tags": {"leisure": "park"}}, {"type": "way", "id": 605099731, "nodes": [5256816344, 5740023421, 5740023422, 5740023423, 5740023424, 5740023425, 5740023426, 5740023427, 5740023428, 5740023429, 6550198469, 5740023430, 5740023431, 5740023432, 5740023433, 5301612233, 5301612232, 5740023434, 5740023435, 5256816344], "tags": {"leisure": "sports_centre", "name": "Parque Desportivo Jo\u00e3o Martins (IOS)"}}, {"type": "way", "id": 608747229, "nodes": [5766825914, 5766825915, 5766825916, 5766825917, 5766825914], "tags": {"access": "customers", "brand": "McDonald's", "leisure": "playground", "name": "McDonald's PlayPlace"}}, {"type": "way", "id": 608767578, "nodes": [5766950240, 5766950241, 5766950242, 5766950243, 5766950240], "tags": {"leisure": "pitch"}}, {"type": "way", "id": 677925439, "nodes": [6347712881, 6347712884, 6347712882, 6347712883, 6347712881], "tags": {"leisure": "pitch"}}, {"type": "way", "id": 677925440, "nodes": [6347712885, 6347712886, 6347712888, 6347712887, 6347712885], "tags": {"leisure": "pitch"}}, {"type": "way", "id": 697461058, "nodes": [6550198472, 6550198473, 6550198474, 6550198475, 6550198476, 6550198477, 6550198478, 6550198479, 6550198480, 6550198481, 6550198482, 6550198483, 6550198484, 6550203799, 6550203785, 6550203800, 6550203786, 6550203801, 6550203804, 6550203787, 6550203805, 6550203802, 6550203806, 6550203788, 6550203807, 6550203803, 6550203808, 6550203789, 6550203809, 6550203810, 12837135659, 12836813680, 6550203790, 6550198470, 6550203794, 6550203796, 6550203797, 6550198471, 12836813664, 6550198472], "tags": {"area": "yes", "leisure": "track", "sport": "running"}}, {"type": "way", "id": 766581557, "nodes": [7159602960, 5032006567]}, {"type": "way", "id": 766581560, "nodes": [5032006567, 1986259630], "tags": {"barrier": "city_wall"}}, {"type": "way", "id": 766581562, "nodes": [1986259630, 7159602960]}, {"type": "way", "id": 1204698120, "nodes": [11165126083, 11165126080, 11165126081, 11165126082, 11165126083], "tags": {"leisure": "garden"}}, {"type": "way", "id": 1204769298, "nodes": [11165862366, 11165862363, 11165862364, 11165862365, 11165862366], "tags": {"leisure": "pitch", "sport": "multi"}}, {"type": "way", "id": 1205348158, "nodes": [11170604576, 11170604573, 11170604574, 11170604575, 11170604576], "tags": {"leisure": "garden"}}, {"type": "way", "id": 1208013260, "nodes": [1746573759, 11193274819, 11193274818, 11193274817, 11193274816, 11193274815, 11193274814, 11193274813, 11193274812, 11193274820, 11193274811, 11193274810, 11193274809, 11193274808, 11193274807, 11193274806, 11193274805, 11193274804, 1746573759], "tags": {"leisure": "playground"}}, {"type": "way", "id": 1208013261, "nodes": [11193274824, 11193274823, 11193274822, 11193274821, 11193274824], "tags": {"leisure": "pitch", "sport": "multi"}}, {"type": "way", "id": 1292157293, "nodes": [1744157072, 11978787978, 11978787979, 11978787980, 11978787981, 11978787982, 11978787983, 11978787984, 11978787985, 11978787986, 11978787987, 11978787970, 11978787973, 11978787974, 11978787975, 11978787976, 11978787977, 11978787971, 11978787972, 1744157072], "tags": {"access": "yes", "leisure": "playground"}}, {"type": "way", "id": 1292157875, "nodes": [1746573785, 11978734839, 11978734840, 11978734841, 1746573785], "tags": {"leisure": "playground"}}, {"type": "way", "id": 1322883164, "nodes": [12241197322, 12241193439, 12241193497, 12241197340, 12241197322], "tags": {"leisure": "playground", "surface": "sand"}}, {"type": "way", "id": 1322883174, "nodes": [12241193435, 12241193478, 12241197330, 12241193450, 12241193435], "tags": {"leisure": "playground", "surface": "sand"}}, {"type": "way", "id": 1386585594, "nodes": [12836813678, 12836813679, 12836813677, 12836813665, 12836813666, 12836813667, 12836813668, 12836813669, 12837135644, 12836813670, 12836813671, 12836813672, 12836813673, 12836813674, 12836813675, 12836813676, 12837135645, 12837135646, 12837135647, 12837135648, 12837135649, 12837135650, 12837135651, 12837135652, 12837135653, 12837135654, 12837135655, 12837135656, 12837135657, 12837135658, 12836813678]}, {"type": "way", "id": 1386636080, "nodes": [12837216397, 12837216398, 12837216399, 12837216400, 12837235901, 12837235902, 12837235903, 12837235904, 12837235905, 12837235906, 12837235907, 12837235908, 12837216397], "tags": {"leisure": "pitch", "name": "Skate Park de Sines", "sport": "skateboard"}}, {"type": "way", "id": 1386675425, "nodes": [12837514959, 12837515000, 12837514960, 12837514961, 12837514966, 12837514967, 12837514968, 12837514969, 12837514962, 12837514963, 12837514964, 12837514965, 12837514999, 12837514990, 12837514991, 12837514992, 12837514993, 12837514994, 12837514995, 12837514996, 12837514997, 12837514998, 12837514958, 12837514959]}, {"type": "way", "id": 1386675426, "nodes": [12837514971, 12837514972, 12837514973, 12837514974, 12837514975, 12837514977, 12837514978, 12837514979, 12837514976, 12837514984, 12837514985, 12837514986, 12837514987, 12837514988, 12837514989, 12837514980, 12837514981, 12837514982, 12837514983, 12837514970, 12837514971], "tags": {"area": "yes", "leisure": "track", "sport": "running"}}, {"type": "relation", "id": 3879105, "members": [{"type": "way", "ref": 292076528, "role": "outer"}, {"type": "way", "ref": 292076533, "role": "inner"}, {"type": "way", "ref": 292076529, "role": "inner"}, {"type": "way", "ref": 292076530, "role": "inner"}], "tags": {"leisure": "track", "surface": "dirt", "type": "multipolygon"}}, {"type": "relation", "id": 10627260, "members": [{"type": "way", "ref": 766581560, "role": "outer"}, {"type": "way", "ref": 766581562, "role": "outer"}, {"type": "way", "ref": 766581557, "role": "outer"}], "tags": {"leisure": "garden", "type": "multipolygon"}}, {"type": "relation", "id": 19131144, "members": [{"type": "way", "ref": 697461058, "role": "outer"}, {"type": "way", "ref": 1386585594, "role": "inner"}], "tags": {"area": "yes", "leisure": "track", "sport": "running", "type": "multipolygon"}}, {"type": "relation", "id": 19131793, "members": [{"type": "way", "ref": 1386675426, "role": "outer"}, {"type": "way", "ref": 1386675425, "role": "inner"}], "tags": {"area": "yes", "leisure": "track", "sport": "running", "type": "multipolygon"}}]}